Workbook

Sheet Build
A1: ONCE HUMAN — Build planner
A2: Yellow cells = fill in with the dropdown lists. Stats, HP and sets are computed automatically. The other sheets hold all the data (filterable).
A4: Slot | B4: Item | C4: Mod | D4: Damage / HP | E4: Fire rate | F4: DPS | G4: Item effect
A5: Primary weapon | B5: KVD - Boom! Boom! | C5: Burning Wrath <Deviant Energy> | D5: =IF(B5="","",INDEX(Weapons!$E$2:$E$133,MATCH(B5,Weapons!$A$2:$A$133,0))) | E5: =IF(B5="","",INDEX(Weapons!$F$2:$F$133,MATCH(B5,Weapons!$A$2:$A$133,0))) | F5: =IF(B5="","",INDEX(Weapons!$G$2:$G$133,MATCH(B5,Weapons!$A$2:$A$133,0))) | G5: =IF(B5="","",INDEX(Weapons!$O$2:$O$133,MATCH(B5,Weapons!$A$2:$A$133,0))&"")
A6: Secondary weapon | B6: Recurve Crossbow | C6: Vulnerability Amplifier <Precision> | D6: =IF(B6="","",INDEX(Weapons!$E$2:$E$133,MATCH(B6,Weapons!$A$2:$A$133,0))) | E6: =IF(B6="","",INDEX(Weapons!$F$2:$F$133,MATCH(B6,Weapons!$A$2:$A$133,0))) | F6: =IF(B6="","",INDEX(Weapons!$G$2:$G$133,MATCH(B6,Weapons!$A$2:$A$133,0))) | G6: =IF(B6="","",INDEX(Weapons!$O$2:$O$133,MATCH(B6,Weapons!$A$2:$A$133,0))&"")
A7: Helmet | C7: Deviation Expert <Deviant Energy> | D7: =IF(B7="","",INDEX(Armor!$E$2:$E$176,MATCH(B7,Armor!$A$2:$A$176,0))) | G7: =IF(B7="","",INDEX(Armor!$B$2:$B$176,MATCH(B7,Armor!$A$2:$A$176,0))&" — "&INDEX(Armor!$G$2:$G$176,MATCH(B7,Armor!$A$2:$A$176,0)))
A8: Mask | B8: Shelterer Mask | C8: Blaze Amplifier <Deviant Energy> | D8: =IF(B8="","",INDEX(Armor!$E$2:$E$176,MATCH(B8,Armor!$A$2:$A$176,0))) | G8: =IF(B8="","",INDEX(Armor!$B$2:$B$176,MATCH(B8,Armor!$A$2:$A$176,0))&" — "&INDEX(Armor!$G$2:$G$176,MATCH(B8,Armor!$A$2:$A$176,0)))
A9: Top | C9: Resist Advantage <Survival> | D9: =IF(B9="","",INDEX(Armor!$E$2:$E$176,MATCH(B9,Armor!$A$2:$A$176,0))) | G9: =IF(B9="","",INDEX(Armor!$B$2:$B$176,MATCH(B9,Armor!$A$2:$A$176,0))&" — "&INDEX(Armor!$G$2:$G$176,MATCH(B9,Armor!$A$2:$A$176,0)))
A10: Gloves | C10: Elemental Overload <Deviant Energy> | D10: =IF(B10="","",INDEX(Armor!$E$2:$E$176,MATCH(B10,Armor!$A$2:$A$176,0))) | G10: =IF(B10="","",INDEX(Armor!$B$2:$B$176,MATCH(B10,Armor!$A$2:$A$176,0))&" — "&INDEX(Armor!$G$2:$G$176,MATCH(B10,Armor!$A$2:$A$176,0)))
A11: Bottoms | B11: Shelterer Pants | C11: Status Amplification <Deviant Energy> | D11: =IF(B11="","",INDEX(Armor!$E$2:$E$176,MATCH(B11,Armor!$A$2:$A$176,0))) | G11: =IF(B11="","",INDEX(Armor!$B$2:$B$176,MATCH(B11,Armor!$A$2:$A$176,0))&" — "&INDEX(Armor!$G$2:$G$176,MATCH(B11,Armor!$A$2:$A$176,0)))
A12: Shoes | C12: Steady Hand <Deviant Energy> | D12: =IF(B12="","",INDEX(Armor!$E$2:$E$176,MATCH(B12,Armor!$A$2:$A$176,0))) | G12: =IF(B12="","",INDEX(Armor!$B$2:$B$176,MATCH(B12,Armor!$A$2:$A$176,0))&" — "&INDEX(Armor!$G$2:$G$176,MATCH(B12,Armor!$A$2:$A$176,0)))
A13: Deviation | B13: Pyro Dino | G13: =IF(B13="","",INDEX(Deviations!$D$2:$D$88,MATCH(B13,Deviations!$A$2:$A$88,0)))
A14: Cradle override | G14: =IF(B14="","",INDEX(Overrides!$C$2:$C$171,MATCH(B14,Overrides!$A$2:$A$171,0)))
A15: Food 1 | G15: =IF(B15="","",INDEX(Food!$E$2:$E$155,MATCH(B15,Food!$A$2:$A$155,0)))
A16: Food 2 | G16: =IF(B16="","",INDEX(Food!$E$2:$E$155,MATCH(B16,Food!$A$2:$A$155,0)))
A18: Equipped mod effects
A19: =IF(C5="","",A5) | B19: =IF(C5="","",C5) | G19: =IF(C5="","",INDEX(Mods!$F$2:$F$819,MATCH(C5,Mods!$A$2:$A$819,0)))
A20: =IF(C6="","",A6) | B20: =IF(C6="","",C6) | G20: =IF(C6="","",INDEX(Mods!$F$2:$F$819,MATCH(C6,Mods!$A$2:$A$819,0)))
A21: =IF(C7="","",A7) | B21: =IF(C7="","",C7) | G21: =IF(C7="","",INDEX(Mods!$F$2:$F$819,MATCH(C7,Mods!$A$2:$A$819,0)))
A22: =IF(C8="","",A8) | B22: =IF(C8="","",C8) | G22: =IF(C8="","",INDEX(Mods!$F$2:$F$819,MATCH(C8,Mods!$A$2:$A$819,0)))
A23: =IF(C9="","",A9) | B23: =IF(C9="","",C9) | G23: =IF(C9="","",INDEX(Mods!$F$2:$F$819,MATCH(C9,Mods!$A$2:$A$819,0)))
A24: =IF(C10="","",A10) | B24: =IF(C10="","",C10) | G24: =IF(C10="","",INDEX(Mods!$F$2:$F$819,MATCH(C10,Mods!$A$2:$A$819,0)))
A25: =IF(C11="","",A11) | B25: =IF(C11="","",C11) | G25: =IF(C11="","",INDEX(Mods!$F$2:$F$819,MATCH(C11,Mods!$A$2:$A$819,0)))
A26: =IF(C12="","",A12) | B26: =IF(C12="","",C12) | G26: =IF(C12="","",INDEX(Mods!$F$2:$F$819,MATCH(C12,Mods!$A$2:$A$819,0)))
A28: Summary
A29: Total armor HP | B29: =SUM(D7:D12)
A30: Combined DPS (2 weapons) | B30: =SUM(F5:F6)
A31: Pieces equipped | B31: =COUNTA(B7:B12)
A33: Sets (pieces worn)
A34: =IF(B7="","",INDEX(Armor!$B$2:$B$176,MATCH(B7,Armor!$A$2:$A$176,0))) | B34: =IF(A34="","",COUNTIF($A$34:$A$39,A34)) | C34: =IF(A34="","",IFERROR(INDEX(Armor!$H$2:$H$176,MATCH(B7,Armor!$A$2:$A$176,0))&"",""))
A35: =IF(B8="","",INDEX(Armor!$B$2:$B$176,MATCH(B8,Armor!$A$2:$A$176,0))) | B35: =IF(A35="","",COUNTIF($A$34:$A$39,A35)) | C35: =IF(A35="","",IFERROR(INDEX(Armor!$H$2:$H$176,MATCH(B8,Armor!$A$2:$A$176,0))&"",""))
A36: =IF(B9="","",INDEX(Armor!$B$2:$B$176,MATCH(B9,Armor!$A$2:$A$176,0))) | B36: =IF(A36="","",COUNTIF($A$34:$A$39,A36)) | C36: =IF(A36="","",IFERROR(INDEX(Armor!$H$2:$H$176,MATCH(B9,Armor!$A$2:$A$176,0))&"",""))
A37: =IF(B10="","",INDEX(Armor!$B$2:$B$176,MATCH(B10,Armor!$A$2:$A$176,0))) | B37: =IF(A37="","",COUNTIF($A$34:$A$39,A37)) | C37: =IF(A37="","",IFERROR(INDEX(Armor!$H$2:$H$176,MATCH(B10,Armor!$A$2:$A$176,0))&"",""))
A38: =IF(B11="","",INDEX(Armor!$B$2:$B$176,MATCH(B11,Armor!$A$2:$A$176,0))) | B38: =IF(A38="","",COUNTIF($A$34:$A$39,A38)) | C38: =IF(A38="","",IFERROR(INDEX(Armor!$H$2:$H$176,MATCH(B11,Armor!$A$2:$A$176,0))&"",""))
A39: =IF(B12="","",INDEX(Armor!$B$2:$B$176,MATCH(B12,Armor!$A$2:$A$176,0))) | B39: =IF(A39="","",COUNTIF($A$34:$A$39,A39)) | C39: =IF(A39="","",IFERROR(INDEX(Armor!$H$2:$H$176,MATCH(B12,Armor!$A$2:$A$176,0))&"",""))
A40: Note: theoretical DPS = damage × fire rate ÷ 60 (no crit or effects). Set name repeated per piece; the number shows how many pieces of that set you wear.

Sheet Weapons
A1: Name | B1: Type | C1: Rarity | D1: Tier | E1: Damage | F1: Fire rate (rpm) | G1: Theoretical DPS | H1: Magazine | I1: Crit rate | J1: Crit DMG | K1: Weakspot DMG | L1: Range | M1: Reload | N1: Ammo | O1: Effect | P1: Crafting recipe | Q1: Bench | R1: Page | S1: Image | T1: Effect name | U1: Mobility | V1: Damage falloff | W1: Compatible overrides | X1: Note
A2: AA12 | B2: Shotgun | C2: Uncommon | D2: 5 | E2: 148 | F2: 180 | G2: 444 | R2: ouvrir | S2: ouvrir
A3: ACS12 - Corrosion | B3: Shotgun | C3: Legendary | D3: 5 | E3: 138 | F3: 180 | G3: 414 | H3: 8 | I3: 8% | J3: 27% | K3: 15% | L3: 7m | M3: 2.4s | N3: Shotgun Ammo | O3: 70% chance to trigger Power Surge with a hit, but will not inflict Power Surge status. Power Surge can deal Crit hit, Power Surge Crit Rate +15%. When Power Surge is triggered, Power Surge Crit DMG +15% for 6s. Effect can stack up to 10 times. Power Surge DMG Factor +15%. | P3: Rifle Receiver I x1, Legendary Pneumatic Action I x1, Fixed Stock I x1, Standard Barrel I x1 | Q3: Weapon Bench | R3: ouvrir | S3: ouvrir | T3: Power Surge | U3: 50 | V3: 7m / 13m | W3: Shotgun Amplify, Precise Shot, Handgun Enhancement, Anti-Void, Anti-Void: Shotgun
A4: ACS12 - Netherworld | B4: Shotgun | C4: Epic | D4: 5 | E4: 124 | F4: 180 | G4: 372 | H4: 8 | I4: 8% | J4: 27% | K4: 15% | L4: 7m | M4: 2.4s | N4: Shotgun Ammo | O4: When all projectiles hit, there is a 50% chance to trigger Fast Gunner. After triggering Fast Gunner 2 times, the next 1 shot will consume an additional 1 bullet and fire an additional 5 projectiles. After reloading when the magazine is empty, the first 12 bullets will have Attack +20%. | R4: ouvrir | S4: ouvrir | U4: 50 | V4: 7m / 13m
A5: ACS12 - Pyroclasm Starter | B5: Shotgun | C5: Legendary | D5: 5 | E5: 138 | F5: 180 | G5: 414 | H5: 8 | I5: 8% | J5: 27% | K5: 15% | L5: 7m | M5: 2.4s | N5: Shotgun Ammo | O5: 27% chance to trigger Burn on hit. 20% chance to generate a Deviant Particle on hit, which can be picked up to enter Charge state. While under Charge upon reloading, replace all ammunition as Dragon's Breath ammo until the next reload. Dragon's Breath: Deals Blaze Elemental Weapon DMG equal to 85% Attack (Burn DMG bonus applies). Upon reloading, expend all Charge to increase Blaze Elemental DMG by 10% until next reload. Each Charge stack expended further increases this by an additional 10%, up to 4 stacks. | P5: Rifle Receiver I x1, Legendary Pneumatic Action I x1, Fixed Stock I x1, Standard Barrel I x1 | Q5: Weapon Bench | R5: ouvrir | S5: ouvrir | T5: Burn | U5: 50 | V5: 7m / 13m | W5: Shotgun Amplify, Precise Shot, Handgun Enhancement, Anti-Void, Anti-Void: Shotgun
A6: AKM | B6: Assault Rifle | C6: Uncommon | D6: 5 | E6: 120 | F6: 600 | G6: 1200 | R6: ouvrir | S6: ouvrir
A7: AUG - Electron Cloud | B7: Assault Rifle | C7: Legendary | D7: 5 | E7: 132 | F7: 720 | G7: 1584 | H7: 40 | I7: 10% | J7: 25% | K7: 60% | L7: 26m | M7: 2.3s | N7: Rifle Ammo | O7: When hitting with a weapon, there is a 30% chance to apply Power Surge to the target. The first weapon hit after reloading creates an electromagnetic status zone with a radius of 4m centered on the target (max 1 at a time) lasting 7s. When triggering Power Surge on a unit withing the zone, 1 electric orb is generated moving in a random direction within the zone. When an electric orb hits an obstacle or an enemy, it bounces, with a single orb bouncing up to 10 times. If it hits an enemy unit, it also deals Shock Elemental DMG of 42% Psi Intensity. Shock Elemental DMG +30%. | R7: ouvrir | U7: 60 | V7: 26m / 73m
A8: AWM | B8: Sniper Rifle | C8: Uncommon | D8: 5 | E8: 850 | F8: 40 | G8: 567 | R8: ouvrir | S8: ouvrir
A9: AWS.338 - Black Panther | B9: Sniper Rifle | C9: Epic | D9: 5 | E9: 1094 | F9: 40 | G9: 729 | H9: 5 | I9: 2% | J9: 26% | K9: 95% | L9: 58m | M9: 3.6s | N9: SR Ammo | O9: After aiming for 3s, trigger Fortress Warfare, cooldown 10s. Attack increases the longer you aim, up to 30%. After triggering Fortress Warfare, gain 3 stacks of Brutal Mayhem and Weakspot DMG +25%. Every shot reduces the effect by 1%. | R9: ouvrir | S9: ouvrir | U9: 44 | V9: 58m / 106m
A10: AWS.338 - Bullseye | B10: Sniper Rifle | C10: Legendary | D10: 5 | E10: 1216 | F10: 40 | G10: 811 | H10: 5 | I10: 2% | J10: 26% | K10: 95% | L10: 58m | M10: 3.6s | N10: SR Ammo | O10: 70% chance to trigger The Bull's Eye with a weakspot hit. After switching weapon, the first hit will trigger The Bull's Eye. With a hit, Weakspot DMG +15% for 10s. Effect can st ack up to 3 times. After defeating an enemy with a weakspot hit, Attack +15% for 20s. | P10: Sniper Rifle Receiver I x1, Legendary Bolt Action I x1, Fixed Stock I x1, Long Barrel I x1 | Q10: Weapon Bench | R10: ouvrir | S10: ouvrir | T10: The Bull's Eye | U10: 44 | V10: 58m / 106m | W10: Sniper Rifle Crit Boost, Speedy Shot, Sniper Rifle Weakspot DMG Boost, Long-Range Enhancement, Anti-Phase
A11: Aurora Fort | B11: LMG | C11: Legendary | D11: 5 | E11: 271 | F11: 700 | G11: 3162 | H11: 90 | L11: 29m | M11: 4.5s | N11: Light Machine Gun Bullet | R11: ouvrir | S11: ouvrir | U11: 33 | V11: 29m / 87m / 30% | W11: LMG Reload Boost, Speedy Shot, Automatic Weapon Enhancement, Anti-Regen, Anti-Coherence
A12: BAR | B12: LMG | C12: Uncommon | D12: 5 | E12: 192 | F12: 400 | G12: 1280 | R12: ouvrir | S12: ouvrir
A13: Baseball Bat | B13: Melee | C13: Rare | D13: 5 | E13: 622 | I13: 5% | J13: 25% | K13: 20% | O13: The first heavy attack that hits a target inflicts Blunt DMG and reduces the target's subsequent DMG dealt by 30% for 15s. Ineffective against bosses and Meta-Humans. | R13: ouvrir | S13: ouvrir
A14: Broken Bottle | B14: Melee | C14: Uncommon | D14: 5 | E14: 430 | R14: ouvrir | S14: ouvrir
A15: Camping Knife | B15: Melee | C15: Rare | D15: 5 | E15: 622 | I15: 5% | J15: 25% | K15: 20% | O15: Melee hits have a 33% chance to inflict additional Melee DMG of 50% Attack. | R15: ouvrir | S15: ouvrir
A16: Compound Bow | B16: Crossbow | C16: Legendary | D16: 5 | E16: 1192 | F16: 90 | G16: 1788 | H16: 1 | I16: 2% | J16: 28% | K16: 70% | L16: 19m | M16: 2.6s | N16: Arrow | O16: Gain Crit Rate +10% and Reload Speed +6 upon hitting a target. This effect stacks up to 3 times and lasts for 6s. Upon defeating a target, gain the maximum number of stacks. At max stacks, enhanced Unstable Bomber is triggered upon hitting a target (can Crit and causes the target to lose balance). Every shot fired increases Unstable Bomber's DMG by 3%, stacking up to 6 times. If a shot misses, existing stacks are halved. Hitting a Weakspot has a 40% chance to automatically reload 1 crossbow bolt. | P16: Copper Ingot x10, Metal Scraps x15, Rusted Part x6, Shabby Fabric x4, Stardust Source x15 | Q16: Weapon Bench | R16: ouvrir | S16: ouvrir | U16: 60 | V16: 19m / 30m | W16: Crossbow DMG Boost, Speedy Shot, Long-Range Enhancement, Anti-Phase, Anti-Coherence: Crossbow
A17: Compound Bow - The Burden of Betrayal | B17: Crossbow | C17: Legendary | D17: 5 | E17: 510 | F17: 65 | G17: 552 | H17: 1 | I17: 5% | J17: 45% | K17: 25% | L17: 19m | M17: 1.8s | N17: Arrow | O17: Attacks always trigger Bounce. Bounce targets +2. Number of Bounces +1 and an addition +1 at full charge. Reload Efficiency +100% When a hit or a Bounce hit lands applies 1 stack of Echo to the target Echo: Max 4 stacks. Displays a highlighted visual effect when at max stacks lasting 15s. At full change, Bounce DMG +20% and Crit Rate +25%. When a Bounce hit lands, deals additional Bounce Weapon DMG equal to Echo stacks x80%. Cooldown per target: 1s. After triggering removes all Echo Stacks from the target. If there are no enemies to Bounce to after a hit, number of Bounces +2. | R17: ouvrir | U17: 58 | V17: 19m / 30m
A18: Critical Pulse | B18: Crossbow | C18: Legendary | D18: 5 | E18: 1192 | F18: 90 | G18: 1788 | H18: 1 | I18: 2% | J18: 28% | K18: 70% | L18: 19m | M18: 2.6s | N18: Arrow | O18: Triggers continous Power Surge on hit, with a 70% chance to generate deviatied particles near the player (pick them up to enter a charged state). Continous Power Surge can trigger every 0.5s within 3s on the current target. Higher stacks shorten the interval (minimum 0.26s), stacking up to 5 times (dealing 60% DMG to the player). While in a charged state, hitting a target consumes one charge to create an orb of lightning: dealing Shock Elemental Status DMG of 75% Psi Intensity to targets within 5m every 0.5s. This damage benefits from Power Surge DMG bonuses and has a 5% chance to generate deviated particles lasting for 3s. Shock Elemental DMG bonus +30%. | P18: Copper Ingot x10, Metal Scraps x15, Rusted Part x6, Shabby Fabric x4, Stardust Source x15 | Q18: Weapon Bench | R18: ouvrir | S18: ouvrir | T18: Power Surge | U18: 60 | V18: 19m / 30m | W18: Crossbow DMG Boost, Speedy Shot, Long-Range Enhancement, Anti-Phase, Anti-Coherence: Crossbow
A19: Crowbar | B19: Melee | C19: Epic | D19: 5 | E19: 630 | R19: ouvrir | S19: ouvrir
A20: DB12 - Backfire | B20: Shotgun | C20: Epic | D20: 5 | E20: 190 | F20: 105 | G20: 332 | H20: 12 | I20: 8% | J20: 28% | K20: 20% | L20: 7m | M20: 0.5s | N20: Shotgun Ammo | O20: Hit the enemy 5 times to trigger Frost Vortex. After hitting the enemies inside the Frost Vortex with your weapon 1 time, the enemy will be Frozen for 3s (cooldown 4s, cannot be frozen again during this time). When hitting Frozen enemies, DMG +60%. | R20: ouvrir | S20: ouvrir | T20: Frost Vortex | U20: 53 | V20: 7m / 13m
A21: DB12 - Raining Cash | B21: Shotgun | C21: Legendary | D21: 5 | E21: 212 | F21: 105 | G21: 371 | H21: 12 | I21: 8% | J21: 28% | K21: 20% | L21: 7m | M21: 0.5s | N21: Shotgun Ammo | O21: Reloading triggers Fortress Warfare, cooldown 10s. The longer Fortress Warfare is maintained, the higher the Attack, up to +40%. While in Fortress Warfare, Crit Rate +30%. While in Fortress Warfare, DMG Reduction +30%. | P21: Bullpup Receiver I x1, Legendary Pump Action I x1, DBSG I (craftable) x1 | Q21: Weapon Bench | R21: ouvrir | S21: ouvrir | T21: Fortress Warfare | U21: 53 | V21: 7m / 13m | W21: Shotgun Amplify, Precise Shot, Handgun Enhancement, Anti-Void, Anti-Void: Shotgun
A22: DBSG | B22: Shotgun | C22: Uncommon | D22: 5 | E22: 190 | F22: 180 | G22: 570 | O22: This weapon doesn't have any unique effects. | R22: ouvrir | S22: ouvrir
A23: DBSG - Doombringer | B23: Shotgun | C23: Legendary | D23: 5 | E23: 238 | F23: 180 | G23: 714 | H23: 2 | I23: 10% | J23: 30% | K23: 25% | L23: 7m | M23: 2.1s | N23: Shotgun Ammo | O23: 30% chance to trigger The Bull's Eye when hitting the enemy. This chance is raised to 80% upon hitting an enemy within 5m. Defeating a marked enemy grants Attack +6 for 60s, up to 5 stacks. After triggering The Bull's Eye, DMG Reduction +5% for 8s, up to 4 stack(s). Crit Rate +30% when hitting marked enemies. | P23: DBSG Receiver I x1, Legendary Pump Action I x1, Fixed Stock I x1, DBSG I (craftable) x1 | Q23: Weapon Bench | R23: ouvrir | S23: ouvrir | T23: The Bull's Eye | U23: 66 | V23: 7m / 13m | W23: Shotgun Amplify, Precise Shot, Handgun Enhancement, Anti-Void, Anti-Void: Shotgun
A24: DBSG - Dual Fury | B24: Shotgun | C24: Epic | D24: 5 | E24: 214 | F24: 180 | G24: 642 | H24: 2 | I24: 10% | J24: 30% | K24: 25% | L24: 7m | M24: 2.1s | N24: Shotgun Ammo | O24: The last shot of each magainze inflicts 1 stack of Burn. If all projectiles hit, inflict an additional 1 stack. After hitting the enemy with all projectiles 4 times, enter a special Burn state where you lose some HP (will not fall below 0)m Attack +20%, and Vulnerability +10% for 8s. Hitting enemies affected by Burn with all projectiles has a 50% chance to refill 1 bullet. | R24: ouvrir | S24: ouvrir | U24: 66 | V24: 7m / 13m
A25: DBSG - Format | B25: Shotgun | C25: Legendary | D25: 5 | E25: 340 | F25: 180 | G25: 1020 | H25: 2 | L25: 7m | M25: 2.1s | N25: Shotgun Ammo | P25: DBSG Receiver I x1, Legendary Pump Action I x1, Fixed Stock I x1, DBSG I (craftable) x1 | Q25: Weapon Bench | R25: ouvrir | S25: ouvrir | U25: 60 | V25: 7m / 13m / 10% | W25: Shotgun Amplify, Precise Shot, Handgun Enhancement, Anti-Void, Anti-Void: Shotgun
A26: DBSG - Old Huntsman | B26: Shotgun | C26: Rare | D26: 5 | E26: 190 | F26: 180 | G26: 570 | H26: 2 | I26: 10% | J26: 30% | K26: 25% | L26: 7m | M26: 2.1s | N26: Shotgun Ammo | O26: 35% chance to trigger The Bull's Eye when hitting a target. DMG +20% to targets affected by The Bull's Eye. | R26: ouvrir | S26: ouvrir | U26: 66 | V26: 7m / 13m
A27: DE .50 | B27: Pistol | C27: Uncommon | D27: 5 | E27: 394 | F27: 190 | G27: 1248 | O27: No special abilites. | R27: ouvrir | S27: ouvrir
A28: DE.50 - Goshawk | B28: Pistol | C28: Rare | D28: 5 | E28: 402 | F28: 190 | G28: 1273 | R28: ouvrir | S28: ouvrir
A29: DE.50 - Jaws | B29: Pistol | C29: Legendary | D29: 5 | E29: 494 | F29: 190 | G29: 1564 | H29: 9 | I29: 6% | J29: 25% | K29: 60% | L29: 20m | M29: 1.8s | N29: Pistol Ammo | O29: Unstable Bomber is triggered every 4 shots. Critical hits count as 1 shots for the above purpose. After hitting a Weakspot, gain Explosion Elemental DMG +30% for 8s. Unstable Bomber can Crit, and has Crit Rate +25%. | P29: Pistol Frame I x1, Legendary Recoil Action I x1, Pistol Slide I x1 | Q29: Weapon Bench | R29: ouvrir | S29: ouvrir | T29: Unstable Bomber | U29: 73 | V29: 20m / 32m | W29: Pistol DMG Boost, Speedy Shot, Handgun Enhancement, Anti-Regen, Anti-Coherence
A30: DE.50 - Wildfire | B30: Pistol | C30: Epic | D30: 5 | E30: 444 | F30: 190 | G30: 1406 | H30: 8 | I30: 6% | J30: 25% | K30: 60% | L30: 20m | M30: 1.8s | N30: Pistol Ammo | O30: 60% chance to trigger The Bull's Eye when hitting a target. There is an 80% chance to spread The Bull's Eye to 1 enemy within a 15m area, Weapon DMG +25% for 10s. When hitting a Weakpoint of marked enemies, Attack +3% for 10s, up to 3 stacks. | R30: ouvrir | S30: ouvrir | T30: The Bull's Eye | U30: 73 | V30: 20m / 32m
A31: DP12 | B31: Shotgun | C31: Uncommon | D31: 5 | E31: 184 | F31: 105 | G31: 322 | R31: ouvrir | S31: ouvrir
A32: EBR-14 - Octopus! Grilled Rings! | B32: Sniper Rifle | C32: Legendary | D32: 5 | E32: 310 | F32: 300 | G32: 1550 | H32: 20 | I32: 5% | J32: 40% | K32: 50% | L32: 51m | M32: 3s | N32: SR Ammo | O32: When the weapon hits, 50% chance to appy Burn to the target. At max stacks, Burn targets generate a fire ring, spreading Burn DMG to enemies within 6 meters at Burn frequency. Burn DMG +75%. Max Burn stacks -3. Crit Rate + 20%. | P32: Sniper Rifle Receiver I x1, Legendary Pneumatic Action I x1, Fixed Stock I x1, Long Barrel I x1 | Q32: Weapon Bench | R32: ouvrir | S32: ouvrir | U32: 50 | V32: 51m / 93m | W32: Sniper Rifle Crit Boost, Speedy Shot, Sniper Rifle Weakspot DMG Boost, Long-Range Enhancement, Anti-Phase
A33: Fate of the Mystic | B33: Pistol | C33: Uncommon | D33: 1 | F33: 190 | G33: 0 | R33: ouvrir | S33: ouvrir
A34: Fine Dagger | B34: Melee | C34: Uncommon | D34: 5 | E34: 495 | R34: ouvrir | S34: ouvrir
A35: Fine Steel Pipe | B35: Melee | C35: Uncommon | D35: 5 | E35: 666 | R35: ouvrir | S35: ouvrir
A36: Flamethrower | B36: Flamethrower | C36: Epic | D36: 5 | E36: 252 | F36: 300 | G36: 1260 | R36: ouvrir | S36: ouvrir
A37: Flare Gun | B37: Pistol | C37: Uncommon | D37: 5 | E37: 40 | F37: 140 | G37: 93 | R37: ouvrir | S37: ouvrir
A38: Frozen Northern Pike | B38: Melee | C38: Epic | D38: 5 | E38: 738 | I38: 5% | J38: 25% | K38: 20% | O38: Impacts and heavy attacks will freeze the primary target and generate a Frost Vortex. This can be triggered once every 4s. Attacking a target with Frost Vortex will recover 5% of lost HP, but consumes 2 additional stamina. | R38: ouvrir | S38: ouvrir
A39: G17 - Cash Only | B39: Pistol | C39: Legendary | D39: 5 | E39: 110 | F39: 720 | G39: 1320 | R39: ouvrir | S39: ouvrir
A40: G17 - Dusty | B40: Pistol | C40: Epic | D40: 5 | E40: 206 | F40: 410 | G40: 1408 | H40: 13 | I40: 8% | J40: 28% | K40: 55% | L40: 13m | M40: 2.1s | N40: Pistol Ammo | O40: 55% chance to trigger Shrapnel when hitting a weakspot. When triggered, Shrapnel no longer ignores already hit parts. Weakspot DMG +15%. | R40: ouvrir | S40: ouvrir | U40: 83 | V40: 13m / 25m
A41: G17 - Hazardous Object | B41: Pistol | C41: Legendary | D41: 5 | E41: 230 | F41: 410 | G41: 1572 | H41: 13 | I41: 8% | J41: 28% | K41: 55% | L41: 13m | M41: 2.1s | N41: Pistol Ammo | O41: Hitting Enemies grants a 20% chance to trigger Unstable Bomber. Reloading time -40%, and the reload action is replaced by throwing your weapon, consuming all ammo to deal Blast DMG to targets within 3m range equal to 50% + consumed ammo x 18% of Psi Intensity, capping at: 450%. The effect benefits from Unstable Bomber's DMG and range bonus, and deals 50% DMG to yourself. Throwing the weapon grants 75% chance to recover 75% of consumed ammo, 25% chance to recover 25% of consumed ammo. Unstable Bomber DMG and Range +10% for 10s each time Unstable Bomber deals damage, up to 50%. | R41: ouvrir | S41: ouvrir | T41: Hazardous Object (Unstable Bomber) | U41: 83 | V41: 13m / 25m | X41: Stats détaillées OHDB (chargeur, recharge, recette) non récupérées : fiche non indexée.
A42: Glock | B42: Pistol | C42: Uncommon | D42: 5 | E42: 196 | F42: 410 | G42: 1339 | R42: ouvrir | S42: ouvrir
A43: HAMR - Brahminy | B43: Sniper Rifle | C43: Legendary | D43: 5 | E43: 840 | F43: 85 | G43: 1190 | H43: 8 | I43: 2% | J43: 30% | K43: 80% | L43: 56m | M43: 3.4s | N43: SR Ammo | O43: 80% chance to trigger Bounce when hitting a Weakspot. When Bounce hits a Weakspot, there is a 35% chance for it to continue to ricochet. If Bounce does not defeat an enemy or there is no target, the next 1 bullets Weapon DMG +20%, up to 5 stacks. Bounce will prioritize enemeis with higher HP. | P43: Sniper Rifle Receiver I x1, Legendary Pneumatic Action I x1, Fixed Stock I x1, Long Barrel I x1 | Q43: Weapon Bench | R43: ouvrir | S43: ouvrir | T43: Bounce | U43: 33 | V43: 56m / 102m | W43: Sniper Rifle Crit Boost, Speedy Shot, Sniper Rifle Weakspot DMG Boost, Long-Range Enhancement, Anti-Phase
A44: HAMR - Crumble | B44: Sniper Rifle | C44: Rare | D44: 5 | E44: 672 | F44: 85 | G44: 952 | H44: 8 | I44: 2% | J44: 30% | K44: 80% | L44: 56m | M44: 4s | N44: SR Ammo | O44: 60% chance to trigger Burn with a weakspot hit. Burn DMG +10%. | R44: ouvrir | S44: ouvrir | U44: 33 | V44: 56m / 102m
A45: HAMR - Hannya | B45: Sniper Rifle | C45: Legendary | D45: 5 | E45: 900 | F45: 85 | G45: 1275 | H45: 8 | L45: 56m | M45: 3.4s | N45: SR Ammo | P45: Sniper Rifle Receiver I x1, Legendary Pneumatic Action I x1, Fixed Stock I x1, Long Barrel I x1 | Q45: Weapon Bench | R45: ouvrir | S45: ouvrir | U45: 33 | V45: 56m / 102m / 10% | W45: Sniper Rifle Crit Boost, Speedy Shot, Sniper Rifle Weakspot DMG Boost, Long-Range Enhancement, Anti-Phase
A46: KAM | B46: Assault Rifle | C46: Uncommon | D46: 5 | E46: 120 | F46: 600 | G46: 1200 | H46: 40 | I46: 6% | J46: 30% | K46: 55% | L46: 24m | M46: 2.4s | N46: Rifle Ammo | O46: This weapon doesn't have any unique effects. | R46: ouvrir | U46: 50 | V46: 24m / 67m
A47: KAM - Abyss Glance | B47: Assault Rifle | C47: Legendary | D47: 5 | E47: 150 | F47: 600 | G47: 1500 | H47: 40 | I47: 6% | J47: 30% | K47: 55% | L47: 27m | M47: 3.1s | N47: Rifle Ammo | O47: Hitting enemies 20 times triggers Frost Vortex. Weakspot hits count as 2 hits. The closer to the center of the Frost Vortex, the higher the Frost Vortex DMG, up to +200%. Frost DMG +30%. | P47: Rifle Receiver I x1, Legendary Pneumatic Action I x1, Fixed Stock I x1, Standard Barrel I x1 | Q47: Weapon Bench | R47: ouvrir | S47: ouvrir | T47: Frost Vortex | U47: 51 | V47: 27m / 76m | W47: Rifle Amplify, Precise Shot
A48: KAM - Crank | B48: Assault Rifle | C48: Epic | D48: 5 | E48: 134 | F48: 600 | G48: 1340 | H48: 40 | I48: 6% | J48: 30% | K48: 55% | L48: 25m | M48: 2.8s | N48: Rifle Ammo | O48: Hitting enemies 7 times triggers Burn. Killing enemies with Burn grants Reload Speed +20% and Burn DMG +15% for 5s. Max Burn stacks +1. | R48: ouvrir | S48: ouvrir | U48: 51 | V48: 25m / 70m
A49: KAM - Pioneer | B49: Assault Rifle | C49: Rare | D49: 5 | E49: 120 | F49: 600 | G49: 1200 | H49: 40 | I49: 6% | J49: 30% | K49: 55% | L49: 24m | M49: 2.8s | N49: Rifle Ammo | O49: 30% chance to trigger Shrapnel with a hit. Shrapnel DMG +60%. | R49: ouvrir | S49: ouvrir | U49: 50 | V49: 24m / 67m
A50: KV-SBR | B50: SMG | C50: Uncommon | D50: 5 | E50: 114 | F50: 1000 | G50: 1900 | R50: ouvrir | S50: ouvrir
A51: KV-SBR- Little Jaws | B51: SMG | C51: Legendary | D51: 5 | E51: 110 | F51: 1000 | G51: 1833 | H51: 30 | I51: 10% | J51: 30% | K51: 45% | L51: 14m | M51: 1.9s | N51: SMG Ammo | O51: Hitting enemies 15 times triggers Unstable Bomber. Unstable Bomber delay +0.3s. When hitting enemies affected by Unstable Bomber, the current Unstable Bomber Final DMG +10%, Weakspot hits double the DMG increase. For every 0.1s of Unstable Bomber delay, Unstable Bomber DMG +20%. | P51: SMG Receiver I x1, Legendary Articulated Action I x1, Folding Stock I x1, Short Barrel I x1 | Q51: Weapon Bench | R51: ouvrir | S51: ouvrir | U51: 66 | V51: 14m / 39m | W51: SMG DMG Boost, Precise Shot, Automatic Weapon Enhancement, Anti-Phase, Anti-Phase: SMG
A52: KV-SBR-Icy Rain | B52: SMG | C52: Epic | D52: 5 | E52: 98 | F52: 1000 | G52: 1633 | H52: 30 | I52: 10% | J52: 30% | K52: 45% | L52: 14m | M52: 1.9s | N52: SMG Ammo | O52: Crit hit grants a 40% chance to trigger Frost Vortex. When Frost Vortex in created, auto-reload 15% of bullets. +1 Frost Vortex. | R52: ouvrir | S52: ouvrir | U52: 66 | V52: 14m / 39m
A53: KVD - Boom! Boom! | B53: LMG | C53: Legendary | D53: 5 | E53: 168 | F53: 500 | G53: 1400 | H53: 100 | I53: 10% | J53: 30% | K53: 40% | L53: 27m | M53: 5.1s | N53: Light Machine Gun Bullet | O53: 18% chance to trigger Burn with a hit. Killing any enemy affected by Burn causes an explosion that deals Blaze DMG of 300% Psi Intensity. The explosion will inflict 1 stack of Burn on hit targets. Blaze DMG +30%. | P53: Rifle Receiver I x1, Legendary Pneumatic Action I x1, Folding Stock I x1, Long Barrel I x1 | Q53: Weapon Bench | R53: ouvrir | S53: ouvrir | T53: Burn | U53: 36 | V53: 27m / 81m | W53: LMG Reload Boost, Speedy Shot, Automatic Weapon Enhancement, Anti-Regen, Anti-Coherence
A54: KVD - Icebreaker | B54: LMG | C54: Rare | D54: 5 | E54: 134 | F54: 500 | G54: 1117 | H54: 100 | I54: 10% | J54: 30% | K54: 40% | L54: 27m | M54: 5.1s | N54: Light Machine Gun Bullet | O54: First hit after reloading triggers Frost Vortex. Frost DMG +30%. | R54: ouvrir | S54: ouvrir | U54: 33 | V54: 27m / 81m
A55: Kukri | B55: Melee | C55: Legendary | D55: 5 | E55: 778 | I55: 5% | J55: 25% | K55: 20% | O55: Defeating a target grants all weapons attack +30% and Crit Rate +15% for 10s. When defeating an enemy with heavy strike, Psi Intensity +20% and restores HP by 200% of Psi Intensity. | R55: ouvrir | S55: ouvrir
A56: Long Axe | B56: Melee | C56: Epic | D56: 5 | E56: 830 | I56: 5% | J56: 25% | K56: 20% | O56: Heavy attacks activate Fortress Warfare up to once every 10s. For every target hit, heavy attacks grant all weapons Crit Rate +8% and Melee Swing Speed +5% for 10s. Effect can stack up to 3 times. | R56: ouvrir | S56: ouvrir
A57: M416 | B57: Assault Rifle | C57: Uncommon | D57: 5 | E57: 120 | F57: 750 | G57: 1500 | R57: ouvrir | S57: ouvrir
A58: M416 - Autumn Equinox | B58: Assault Rifle | C58: Epic | D58: 5 | E58: 114 | F58: 750 | G58: 1425 | H58: 36 | I58: 6% | J58: 27% | K58: 60% | L58: 26m | M58: 2.3s | N58: Rifle Ammo | O58: Trigger Fortress Warfare after 7 hits. Cooldown: 15s. In the Fortress Warfare area, recover 4% of max HP per second. When HP is above 75%, Weapon DMG + 25%. | R58: ouvrir | S58: ouvrir | U58: 55 | V58: 26m / 73m
A59: M416 - Scorched Earth | B59: Assault Rifle | C59: Rare | D59: 5 | E59: 100 | F59: 750 | G59: 1250 | H59: 36 | I59: 6% | J59: 27% | K59: 60% | M59: 2.3s | N59: Rifle Ammo | O59: 12% chance to trigger Burn on hit. Burn DMG +10%. | R59: ouvrir | S59: ouvrir | U59: 55
A60: M416 - Silent Anabasis | B60: Assault Rifle | C60: Legendary | D60: 5 | E60: 126 | F60: 750 | G60: 1575 | H60: 36 | I60: 6% | J60: 27% | K60: 60% | L60: 26m | M60: 2.3s | N60: Rifle Ammo | O60: 10% chance to trigger Frost Vortex on hit. Hitting a target with Frost Vortex generates an Ice Crystal. Cooldown: 1.5 seconds. Ice Crystals automatically shatter after 15 seconds, dealing Frost Elemental Status DMG equal to 100% Psi Intensity to nearby targets (Frost Vortex DMG bonus applies). Ice Crystals can also be shattered by shooting them, which increases the DMG they deal to 300% Psi Intensity (deal 60% DMG instead to players). Increases Frost Elemental DMG by 60%. Increases it by an additional +20% for every Ice Crystal shattered for 10 seconds, stacking up to 15 times. | P60: Rifle Receiver I x1, Legendary Pneumatic Action I x1, Folding Stock I x1, Standard Barrel I x1 | Q60: Weapon Bench | R60: ouvrir | S60: ouvrir | T60: Frost Vortex / Ice Crystals | U60: 55 | V60: 26m / 73m | W60: Rifle Amplify, Precise Shot
A61: M82A1 | B61: Sniper Rifle | C61: Uncommon | D61: 5 | E61: 584 | F61: 85 | G61: 827 | R61: ouvrir | S61: ouvrir
A62: M870 | B62: Shotgun | C62: Uncommon | D62: 5 | E62: 250 | F62: 80 | G62: 333 | R62: ouvrir | S62: ouvrir
A63: MG4 | B63: LMG | C63: Uncommon | D63: 5 | E63: 96 | F63: 700 | G63: 1120 | H63: 75 | I63: 8% | J63: 30% | K63: 35% | L63: 30m | M63: 3.5s | N63: Light Machine Gun Bullet | O63: This weapon doesn't have any unique effects. | R63: ouvrir | S63: ouvrir | U63: 30 | V63: 30m / 90m
A64: MG4 - Conflicting Memories | B64: LMG | C64: Legendary | D64: 5 | E64: 124 | F64: 700 | G64: 1447 | H64: 75 | I64: 8% | J64: 30% | K64: 35% | L64: 31m | M64: 4.1s | N64: Light Machine Gun Bullet | O64: Trigger Shrapnel after 12 shot(s) on target. For every 40 magazine capacity, parts hit by Shrapnel +1, up to +4. For every 15 magazine capacity in excess of 100, Shrapnel DMG +8%. Magazine capacity +40. | P64: Rifle Receiver I x1, Legendary Pneumatic Action I x1, Folding Stock I x1, Long Barrel I x1 | Q64: Weapon Bench | R64: ouvrir | S64: ouvrir | U64: 33 | V64: 31m / 93m | W64: LMG Reload Boost, Speedy Shot, Automatic Weapon Enhancement, Anti-Regen, Anti-Coherence
A65: MG4 - Mr Squid | B65: LMG | C65: Epic | D65: 5 | E65: 110 | F65: 700 | G65: 1283 | H65: 75 | I65: 8% | J65: 30% | K65: 35% | L65: 31m | M65: 3.5s | N65: Light Machine Gun Bullet | O65: Crit hits have a 90% chance to trigger Bounce. When Bounce hits, Weapon DMG +2%, up to 50 stacks. 1 stack is removed every 5s. After continuously firing for 2s, Bounce targets +1. | R65: ouvrir | S65: ouvrir | U65: 31 | V65: 31m / 93m
A66: MG4 - Predator | B66: LMG | C66: Legendary | D66: 5 | E66: 124 | F66: 700 | G66: 1447 | H66: 75 | I66: 8% | J66: 30% | K66: 35% | L66: 31m | M66: 4.1s | N66: Light Machine Gun Bullet | O66: 40% chance to trigger Fast Gunner when hitting the enemy. Whenever Fast Gunner stacks reach a multiple of 5, gain infinite ammo for 0.5s. Hitting the same target consecutively grants Weapon DMG +2% with each hit, up to +40%. Effect resets when the target is changed. When the remaining bullets is more than 50% of the magazine capacity, Attack +40%. | P66: Rifle Receiver I x1, Legendary Pneumatic Action I x1, Folding Stock I x1, Long Barrel I x1 | Q66: Weapon Bench | R66: ouvrir | S66: ouvrir | T66: Fast Gunner | U66: 33 | V66: 31m / 93m | W66: LMG Reload Boost, Speedy Shot, Automatic Weapon Enhancement, Anti-Regen, Anti-Coherence
A67: MG4 - Sandstorm | B67: LMG | C67: Rare | D67: 5 | E67: 124 | F67: 700 | G67: 1447 | R67: ouvrir | S67: ouvrir
A68: MG4 - Wrath of Hades | B68: LMG | C68: Epic | D68: 5 | E68: 110 | F68: 700 | G68: 1283 | H68: 75 | I68: 8% | J68: 30% | K68: 35% | L68: 31m | M68: 3.5s | N68: Light Machine Gun Bullet | O68: 40% chance to trigger Fast Gunner when hitting a target. Fast Gunner refills 1 bullet from inventory to the secondary weapon. After defeating a target, restores 1 bullet from inventory to the secondary weapon. | R68: ouvrir | S68: ouvrir | U68: 33 | V68: 31m / 93m
A69: MGL | B69: Rocket Launcher | C69: Epic | D69: 5 | E69: 1066 | F69: 140 | G69: 2487 | H69: 6 | I69: 4% | J69: 30% | K69: 35% | L69: 34m | M69: 7s | N69: Grenade | O69: 6 consecutive hits from a single magazine grant Tumult and trigger Fortress Warfare at the next reload. While in Fortress Warfare, refill 1 grenade every 1s. | R69: ouvrir | S69: ouvrir | U69: 42 | V69: 34m / 102m
A70: MK14 | B70: Sniper Rifle | C70: Uncommon | D70: 5 | E70: 338 | F70: 300 | G70: 1690 | R70: ouvrir | S70: ouvrir
A71: MPS5 | B71: SMG | C71: Uncommon | D71: 5 | E71: 136 | F71: 750 | G71: 1700 | R71: ouvrir | S71: ouvrir
A72: MPS5 - Blue Tiger | B72: SMG | C72: Rare | D72: 5 | E72: 114 | F72: 750 | G72: 1425 | H72: 30 | I72: 8% | J72: 30% | K72: 55% | L72: 17m | M72: 2.4s | N72: SMG Ammo | O72: 30% chance to trigger Bounce with a hit. Bounce DMG +60%. | R72: ouvrir | S72: ouvrir | U72: 60 | V72: 17m / 47m
A73: MPS5 - Kumawink | B73: SMG | C73: Legendary | D73: 5 | E73: 142 | F73: 750 | G73: 1775 | H73: 30 | I73: 8% | J73: 30% | K73: 55% | L73: 18m | M73: 2.3s | N73: SMG Ammo | O73: 25% chance of triggering Bounce with a hit. Bounce trigger factor for that shot is +60% (based on weapon's Trigger Chance) with a weakspot hit. Bounce Base DMG +50%. When magazine capacity is below 50%, Bounce Trigger Count +1. | P73: SMG Receiver I x1, Legendary Blowback Action I x1, Telescoping Stock I x1, Standard Barrel I x1 | Q73: Weapon Bench | R73: ouvrir | S73: ouvrir | T73: Bounce | U73: 60 | V73: 18m / 50m | W73: SMG DMG Boost, Precise Shot, Automatic Weapon Enhancement, Anti-Phase, Anti-Phase: SMG
A74: MPS5 - Primal Rage | B74: SMG | C74: Legendary | D74: 5 | E74: 142 | F74: 750 | G74: 1775 | H74: 30 | I74: 8% | J74: 30% | K74: 55% | L74: 18m | M74: 2.3s | N74: SMG Ammo | O74: 35% chance of gaining a stack of Fast Gunner effect on hit. When the magazine has 1 bullet(s) left, 1% of max HP and spare ammo can be consumed to continue friging (HP can't drop below 1). Each hit restores HP equal to 0.1% X Fast Gunner stacks. Every 1% HP change grants 1% Weapon DMG boost, lasting for 5s; each stack duration is independent, up to 80%. | P74: SMG Receiver I x1, Legendary Blowback Action I x1, Telescoping Stock I x1, Standard Barrel I x1 | Q74: Weapon Bench | R74: ouvrir | S74: ouvrir | U74: 60 | V74: 18m / 50m | W74: SMG DMG Boost, Precise Shot, Automatic Weapon Enhancement, Anti-Phase, Anti-Phase: SMG
A75: MPS7 | B75: SMG | C75: Uncommon | D75: 5 | E75: 100 | F75: 850 | G75: 1417 | H75: 35 | I75: 8% | J75: 30% | K75: 50% | L75: 15m | M75: 2.2s | N75: SMG Ammo | O75: This weapon doesn't have any unique effects. | R75: ouvrir | S75: ouvrir | U75: 68 | V75: 15m / 41m
A76: MPS7 - Chaos Domain | B76: SMG | C76: Legendary | D76: 5 | E76: 184 | F76: 850 | G76: 2607 | H76: 35 | L76: 16m | M76: 3s | N76: SMG Ammo | P76: SMG Receiver I x1, Legendary Recoil Action I x1, Telescoping Stock I x1, Short Barrel I x1 | Q76: Weapon Bench | R76: ouvrir | S76: ouvrir | U76: 68 | V76: 16m / 44m / 30% | W76: SMG DMG Boost, Precise Shot, Automatic Weapon Enhancement, Anti-Phase, Anti-Phase: SMG
A77: MPS7 - Div-Evo | B77: SMG | C77: Epic | D77: 5 | E77: 112 | F77: 850 | G77: 1587 | H77: 35 | I77: 8% | J77: 30% | K77: 50% | L77: 16m | M77: 2.1s | N77: SMG Ammo | O77: 25% chance to trigger Shrapnel. Any defeat increases the chance of triggering Shrapnel by 80% for 12s. Hitting a Weakspot grants Shrapnel target parts +1 for 4s. | R77: ouvrir | S77: ouvrir | U77: 68 | V77: 16m / 44m
A78: MPS7 - Focus | B78: SMG | C78: Rare | D78: 5 | E78: 118 | F78: 850 | G78: 1672 | R78: ouvrir | S78: ouvrir
A79: MPS7 - Outer Space | B79: SMG | C79: Legendary | D79: 5 | E79: 126 | F79: 850 | G79: 1785 | H79: 35 | I79: 8% | J79: 30% | K79: 50% | L79: 16m | M79: 3s | N79: SMG Ammo | O79: 25% chance to trigger Power Surge when hitting the enemy. After defeating an enemy, Power Surge trigger factor +30% (based on weapon's Trigger Chance) for 12s. After reloading, Power Surge trigger factor +40% (based on weapon's Trigger Chance) for 3s. Power Surge trigger factor +40% (based on weapon's Trigger Chance). | P79: SMG Receiver I x1, Legendary Blowback Action I x1, Telescoping Stock I x1, Standard Barrel I x1 | Q79: Weapon Bench | R79: ouvrir | S79: ouvrir | T79: Power Surge | U79: 74 | V79: 16m / 44m | W79: SMG DMG Boost, Precise Shot, Automatic Weapon Enhancement, Anti-Phase, Anti-Phase: SMG
A80: MPS7 - Urban Ninja | B80: SMG | C80: Rare | D80: 5 | E80: 118 | F80: 850 | G80: 1672 | R80: ouvrir | S80: ouvrir
A81: Machete | B81: Melee | C81: Uncommon | D81: 5 | E81: 560 | R81: ouvrir | S81: ouvrir
A82: Metal Baseball Bat | B82: Melee | C82: Rare | D82: 5 | E82: 792 | R82: ouvrir | S82: ouvrir
A83: Military Dagger | B83: Melee | C83: Rare | D83: 5 | E83: 491 | R83: ouvrir | S83: ouvrir
A84: Military Shovel | B84: Melee | C84: Rare | D84: 5 | E84: 590 | R84: ouvrir | S84: ouvrir
A85: Morgan | B85: Shotgun | C85: Uncommon | D85: 1 | E85: 44 | F85: 110 | G85: 81 | R85: ouvrir | S85: ouvrir
A86: Nail Gun | B86: SMG | C86: Uncommon | D86: 5 | E86: 180 | F86: 400 | G86: 1200 | R86: ouvrir | S86: ouvrir
A87: Northern Pike | B87: Melee | C87: Rare | D87: 5 | E87: 656 | I87: 5% | J87: 25% | K87: 20% | O87: This thing costs so much sanity. A hit consumes 5 Sanity and deals Blunt DMG, Psi Intensity +5%. Effect lasts for 3s and can stack up to 5 times. | R87: ouvrir | S87: ouvrir
A88: OIC-8 - Last Carnival | B88: Assault Rifle | C88: Epic | D88: 5 | E88: 120 | F88: 750 | G88: 1500 | R88: ouvrir | S88: ouvrir
A89: Old Baseball Bat | B89: Melee | C89: Uncommon | D89: 5 | E89: 792 | R89: ouvrir | S89: ouvrir
A90: Old Machete | B90: Melee | C90: Uncommon | D90: 5 | E90: 560 | R90: ouvrir | S90: ouvrir
A91: P90 | B91: SMG | C91: Uncommon | D91: 5 | E91: 96 | F91: 900 | G91: 1440 | R91: ouvrir | S91: ouvrir
A92: PDW90 - Holographic Resonance | B92: SMG | C92: Legendary | D92: 5 | E92: 90 | F92: 900 | G92: 1350 | H92: 50 | I92: 8% | J92: 45% | K92: 30% | L92: 17m | M92: 2.2s | N92: SMG Ammo | O92: 20% chance to apply The Bull's Eye on hit. Every 12 hits, triggers AoE DMG dealing Weapon DMG equal to 800% Attack to enemies within an 8m radius (30% damage against Metas). When hitting targets with the Bull's Eye with AoE DMG, reloads 3% ammo, up to 15%. Crit Rate + 20% against targets with The Bull's Eye. | P92: SMG Receiver I x1, Legendary Blowback Action I x1, Telescoping Stock I x1, Standard Barrel I x1 | Q92: Weapon Bench | R92: ouvrir | S92: ouvrir | U92: 77 | V92: 17m / 47m | W92: SMG DMG Boost, Precise Shot, Automatic Weapon Enhancement, Anti-Phase, Anti-Phase: SMG
A93: QBJ97 - Fiery Trees and Silver Flowers | B93: LMG | C93: Legendary | D93: 5 | O93: Weapon hits have a 8% chance to apply Unstable Bomber to the target. Weapon hits have a 8% chance to launch a missile at the target, dealing Unstable Bomber damage equal to 500% Psi Intensity. The missile launch chance increases with successive shots and resets when firing stops. Missiles have a 5% chance to apply Unstable Bomber to the target. When a missile explodes, your weapon gains a stack of Spark. Spark : Recoil and camera shake decrease by 5% for 4s. Max 5 stacks. When Spark stacks are maxed, the chance of bullets and missiles to trigger Unstable Bomber increases by and additional 3%. | R93: ouvrir
A94: R500 | B94: Pistol | C94: Uncommon | D94: 5 | E94: 470 | F94: 145 | G94: 1136 | R94: ouvrir | S94: ouvrir
A95: R500 - Hammerhead Shark | B95: Pistol | C95: Epic | D95: 5 | E95: 588 | F95: 145 | G95: 1421 | H95: 5 | I95: 4% | J95: 25% | K95: 65% | L95: 23m | M95: 2.3s | N95: Pistol Ammo | O95: 80% chance to trigger Power Surge when hitting a weakspot. When hitting an enemy that is affected by Power Surge, deal 100% Psi Intesity Shock DMG to all enemies affected by Power Surge in the area. For every 4 Shock DMG dealt, automatically refill 1 ammo. | R95: ouvrir | S95: ouvrir | U95: 68 | V95: 23m / 37m
A96: R500 - Hunter | B96: Pistol | C96: Rare | D96: 5 | E96: 524 | F96: 145 | G96: 1266 | O96: 30% chance to trigger Fast Gunner when hitting a target. Fast Gunner grants Weapon DMG +30% for 3s. | R96: ouvrir | S96: ouvrir
A97: R500 - Interfade | B97: Pistol | C97: Epic | D97: 5 | E97: 568 | F97: 145 | G97: 1373 | R97: ouvrir | S97: ouvrir
A98: R500 - Memento | B98: Pistol | C98: Legendary | D98: 5 | E98: 654 | F98: 145 | G98: 1580 | H98: 5 | I98: 4% | J98: 25% | K98: 65% | L98: 23m | M98: 2.3s | N98: Pistol Ammo | O98: Hits grant a 36% chance to trigger Fast Gunner. Chance doubles with a weakspot hit. When Fast Gunner is is triggered, 1 bullet will be reloaded to your magazine. Each shot has a 40% chance to consume 1 more bullets. When extra bullets are consumed, Attack +80%. | P98: R500 Frame I x1, Legendary Revolver Action I x1, R500 Magazine I x1 | Q98: Weapon Bench | R98: ouvrir | S98: ouvrir | U98: 68 | V98: 23m / 37m | W98: Pistol DMG Boost, Speedy Shot, Handgun Enhancement, Anti-Regen, Anti-Coherence
A99: RPD | B99: LMG | C99: Uncommon | D99: 5 | E99: 126 | F99: 500 | G99: 1050 | R99: ouvrir | S99: ouvrir
A100: RPG7 Rocket Launcher | B100: Rocket Launcher | C100: Rare | D100: 5 | E100: 1144 | F100: 40 | G100: 763 | H100: 1 | I100: 3% | J100: 25% | K100: 25% | L100: 34m | M100: 2.6s | N100: Rocket | O100: This weapon doesn't have any unique effects. | R100: ouvrir | S100: ouvrir | U100: 26 | V100: 34m / 102m
...

Sheet Armor
A1: Name | B1: Set | C1: Slot | D1: Rarity | E1: HP | F1: Pollution resist | G1: Effect | H1: Set bonus | I1: Crafting recipe | J1: Bench | K1: Page | L1: Image
A2: Agent Pants | B2: Agent | C2: Bottoms | D2: Epic | E2: 130 | F2: 21 | H2: 1p : Head DMG Reduction +10.0%. | 2p : Weakspot DMG +10.0%. | 3p : Get Bullet Saver effect with every precise kill, Weakspot DMG +15% for 8s. Effect can stack up to 3 times. | 4p : Increase Reload Speed by 20% after killing an enemy; Fire Rate +10% when killing with a Weakspot hit. Effect removed when reloading or switching weapons. | K2: ouvrir | L2: ouvrir
A3: Agent Gloves | B3: Agent | C3: Gloves | D3: Epic | E3: 81 | F3: 21 | H3: 1p : Head DMG Reduction +10.0%. | 2p : Weakspot DMG +10.0%. | 3p : Get Bullet Saver effect with every precise kill, Weakspot DMG +15% for 8s. Effect can stack up to 3 times. | 4p : Increase Reload Speed by 20% after killing an enemy; Fire Rate +10% when killing with a Weakspot hit. Effect removed when reloading or switching weapons. | K3: ouvrir | L3: ouvrir
A4: Agent Helmet | B4: Agent | C4: Helmet | D4: Epic | E4: 54 | F4: 21 | H4: 1p : Head DMG Reduction +10.0%. | 2p : Weakspot DMG +10.0%. | 3p : Get Bullet Saver effect with every precise kill, Weakspot DMG +15% for 8s. Effect can stack up to 3 times. | 4p : Increase Reload Speed by 20% after killing an enemy; Fire Rate +10% when killing with a Weakspot hit. Effect removed when reloading or switching weapons. | K4: ouvrir | L4: ouvrir
A5: Agent Mask | B5: Agent | C5: Mask | D5: Epic | E5: 27 | F5: 28 | H5: 1p : Head DMG Reduction +10.0%. | 2p : Weakspot DMG +10.0%. | 3p : Get Bullet Saver effect with every precise kill, Weakspot DMG +15% for 8s. Effect can stack up to 3 times. | 4p : Increase Reload Speed by 20% after killing an enemy; Fire Rate +10% when killing with a Weakspot hit. Effect removed when reloading or switching weapons. | K5: ouvrir | L5: ouvrir
A6: Agent Shoes | B6: Agent | C6: Shoes | D6: Epic | E6: 108 | F6: 21 | H6: 1p : Head DMG Reduction +10.0%. | 2p : Weakspot DMG +10.0%. | 3p : Get Bullet Saver effect with every precise kill, Weakspot DMG +15% for 8s. Effect can stack up to 3 times. | 4p : Increase Reload Speed by 20% after killing an enemy; Fire Rate +10% when killing with a Weakspot hit. Effect removed when reloading or switching weapons. | K6: ouvrir | L6: ouvrir
A7: Agent Top | B7: Agent | C7: Top | D7: Epic | E7: 140 | F7: 28 | H7: 1p : Head DMG Reduction +10.0%. | 2p : Weakspot DMG +10.0%. | 3p : Get Bullet Saver effect with every precise kill, Weakspot DMG +15% for 8s. Effect can stack up to 3 times. | 4p : Increase Reload Speed by 20% after killing an enemy; Fire Rate +10% when killing with a Weakspot hit. Effect removed when reloading or switching weapons. | K7: ouvrir | L7: ouvrir
A8: Bastille Pants | B8: Bastille | C8: Bottoms | D8: Legendary | E8: 144 | F8: 21 | H8: 1p : When HP is above 70%, Weapon DMG +10%. | 2p : Reload Speed +20.0%. | 3p : Stay crouched and immobile for 0.5 seconds to enter Bastille state, which grants +40% Weapon DMG. Upon exiting Bastille state, sprinting is disabled for 3 seconds and C stamina consumption is increased by 100%. | 4p : 3s after exiting Bastille state, gain 1 stack of Armor per second, up to 60 stacks. While in Bastille state, each stack of Armor provides a Shield equal to 1% of max HP. If the shield drops to 0 during Bastille state, you gain a 30% Vulnerability effect. | K8: ouvrir | L8: ouvrir
A9: Bastille Gloves | B9: Bastille | C9: Gloves | D9: Legendary | E9: 90 | F9: 21 | H9: 1p : When HP is above 70%, Weapon DMG +10%. | 2p : Reload Speed +20.0%. | 3p : Stay crouched and immobile for 0.5 seconds to enter Bastille state, which grants +40% Weapon DMG. Upon exiting Bastille state, sprinting is disabled for 3 seconds and C stamina consumption is increased by 100%. | 4p : 3s after exiting Bastille state, gain 1 stack of Armor per second, up to 60 stacks. While in Bastille state, each stack of Armor provides a Shield equal to 1% of max HP. If the shield drops to 0 during Bastille state, you gain a 30% Vulnerability effect. | K9: ouvrir | L9: ouvrir
A10: Bastille Helmet | B10: Bastille | C10: Helmet | D10: Legendary | E10: 60 | F10: 21 | H10: 1p : When HP is above 70%, Weapon DMG +10%. | 2p : Reload Speed +20.0%. | 3p : Stay crouched and immobile for 0.5 seconds to enter Bastille state, which grants +40% Weapon DMG. Upon exiting Bastille state, sprinting is disabled for 3 seconds and C stamina consumption is increased by 100%. | 4p : 3s after exiting Bastille state, gain 1 stack of Armor per second, up to 60 stacks. While in Bastille state, each stack of Armor provides a Shield equal to 1% of max HP. If the shield drops to 0 during Bastille state, you gain a 30% Vulnerability effect. | K10: ouvrir | L10: ouvrir
A11: Bastille Mask | B11: Bastille | C11: Mask | D11: Legendary | E11: 30 | F11: 28 | H11: 1p : When HP is above 70%, Weapon DMG +10%. | 2p : Reload Speed +20.0%. | 3p : Stay crouched and immobile for 0.5 seconds to enter Bastille state, which grants +40% Weapon DMG. Upon exiting Bastille state, sprinting is disabled for 3 seconds and C stamina consumption is increased by 100%. | 4p : 3s after exiting Bastille state, gain 1 stack of Armor per second, up to 60 stacks. While in Bastille state, each stack of Armor provides a Shield equal to 1% of max HP. If the shield drops to 0 during Bastille state, you gain a 30% Vulnerability effect. | K11: ouvrir | L11: ouvrir
A12: Bastille Shoes | B12: Bastille | C12: Shoes | D12: Legendary | E12: 120 | F12: 21 | H12: 1p : When HP is above 70%, Weapon DMG +10%. | 2p : Reload Speed +20.0%. | 3p : Stay crouched and immobile for 0.5 seconds to enter Bastille state, which grants +40% Weapon DMG. Upon exiting Bastille state, sprinting is disabled for 3 seconds and C stamina consumption is increased by 100%. | 4p : 3s after exiting Bastille state, gain 1 stack of Armor per second, up to 60 stacks. While in Bastille state, each stack of Armor provides a Shield equal to 1% of max HP. If the shield drops to 0 during Bastille state, you gain a 30% Vulnerability effect. | K12: ouvrir | L12: ouvrir
A13: Bastille Jacket | B13: Bastille | C13: Top | D13: Legendary | E13: 156 | F13: 28 | H13: 1p : When HP is above 70%, Weapon DMG +10%. | 2p : Reload Speed +20.0%. | 3p : Stay crouched and immobile for 0.5 seconds to enter Bastille state, which grants +40% Weapon DMG. Upon exiting Bastille state, sprinting is disabled for 3 seconds and C stamina consumption is increased by 100%. | 4p : 3s after exiting Bastille state, gain 1 stack of Armor per second, up to 60 stacks. While in Bastille state, each stack of Armor provides a Shield equal to 1% of max HP. If the shield drops to 0 during Bastille state, you gain a 30% Vulnerability effect. | K13: ouvrir | L13: ouvrir
... A49: Falcon Jacket | B49: Falcon | C49: Top | D49: Epic | E49: 140 | F49: 28 | H49: 1p : Rolling Stamina cost -20%. | 2p : Crit DMG +12.0%. | 3p : When Stamina is over 90%, increase Crit Rate by 5% and Crit DMG by 20%. | 4p : Max Stamina +25. Recover 30 Stamina instantly with a kill. | K49: ouvrir | L49: ouvrir
A50: Ghost Link Pants | B50: Ghost Link | C50: Bottoms | D50: Legendary | E50: 1770 | F50: 21 | H50: 1p : Increases Crit Rate by 3%. | 2p : Reload Efficiency +15%. | 3p : When dealing Weapon DMG, you gain 1 stack of Sync: Weapon DMG +3%. Stacks up to 10 times. Last 5s. | 4p : When Sync reaches 10 stacks, attacking an enemy applies Overload. Overload: Deals Status DMG equal to 50% of Psi Intensity every second to the target and enemies within 3m. Last 5s. | K50: ouvrir
A51: Ghost Link Gloves | B51: Ghost Link | C51: Gloves | D51: Legendary | E51: 1106 | F51: 21 | H51: 1p : Increases Crit Rate by 3%. | 2p : Reload Efficiency +15%. | 3p : When dealing Weapon DMG, you gain 1 stack of Sync: Weapon DMG +3%. Stacks up to 10 times. Last 5s. | 4p : When Sync reaches 10 stacks, attacking an enemy applies Overload. Overload: Deals Status DMG equal to 50% of Psi Intensity every second to the target and enemies within 3m. Last 5s. | K51: ouvrir
A52: Ghost Link Helmet | B52: Ghost Link | C52: Helmet | D52: Legendary | E52: 738 | F52: 21 | H52: 1p : Increases Crit Rate by 3%. | 2p : Reload Efficiency +15%. | 3p : When dealing Weapon DMG, you gain 1 stack of Sync: Weapon DMG +3%. Stacks up to 10 times. Last 5s. | 4p : When Sync reaches 10 stacks, attacking an enemy applies Overload. Overload: Deals Status DMG equal to 50% of Psi Intensity every second to the target and enemies within 3m. Last 5s. | K52: ouvrir
A53: Ghost Link Mask | B53: Ghost Link | C53: Mask | D53: Legendary | E53: 369 | F53: 28 | H53: 1p : Increases Crit Rate by 3%. | 2p : Reload Efficiency +15%. | 3p : When dealing Weapon DMG, you gain 1 stack of Sync: Weapon DMG +3%. Stacks up to 10 times. Last 5s. | 4p : When Sync reaches 10 stacks, attacking an enemy applies Overload. Overload: Deals Status DMG equal to 50% of Psi Intensity every second to the target and enemies within 3m. Last 5s. | K53: ouvrir
A54: Ghost Link Shoes | B54: Ghost Link | C54: Shoes | D54: Legendary | E54: 1475 | F54: 21 | H54: 1p : Increases Crit Rate by 3%. | 2p : Reload Efficiency +15%. | 3p : When dealing Weapon DMG, you gain 1 stack of Sync: Weapon DMG +3%. Stacks up to 10 times. Last 5s. | 4p : When Sync reaches 10 stacks, attacking an enemy applies Overload. Overload: Deals Status DMG equal to 50% of Psi Intensity every second to the target and enemies within 3m. Last 5s. | K54: ouvrir
A55: Ghost Link Vest | B55: Ghost Link | C55: Top | D55: Legendary | E55: 1918 | F55: 28 | H55: 1p : Increases Crit Rate by 3%. | 2p : Reload Efficiency +15%. | 3p : When dealing Weapon DMG, you gain 1 stack of Sync: Weapon DMG +3%. Stacks up to 10 times. Last 5s. | 4p : When Sync reaches 10 stacks, attacking an enemy applies Overload. Overload: Deals Status DMG equal to 50% of Psi Intensity every second to the target and enemies within 3m. Last 5s. | K55: ouvrir
A56: Gravity Tide Pants | B56: Gravity Tide | C56: Bottoms | D56: Legendary | E56: 144 | F56: 21 | H56: 1p : Jump Height +10%. | 2p : Magazine Capacity Bonus 15%. | 3p : When airborne gain 20% monster DMG Reduction; for every 5 meters moved in the air, gain 1 stack of Upper Hand increasing Weapon and Status DMG by +1,5% up to a maximum of 15 stacks. Loose one stack of Upper Hand every 5s. | 4p : When Upper Hand exceeds 10 stacks, Weapon and Status damage +10%; After moving 30 meters in the air, Upper Hand will stop decaying for 20s. | K56: ouvrir | L56: ouvrir
A57: Gravity Tide Gloves | B57: Gravity Tide | C57: Gloves | D57: Legendary | E57: 90 | F57: 21 | H57: 1p : Jump Height +10%. | 2p : Magazine Capacity Bonus 15%. | 3p : When airborne gain 20% monster DMG Reduction; for every 5 meters moved in the air, gain 1 stack of Upper Hand increasing Weapon and Status DMG by +1,5% up to a maximum of 15 stacks. Loose one stack of Upper Hand every 5s. | 4p : When Upper Hand exceeds 10 stacks, Weapon and Status damage +10%; After moving 30 meters in the air, Upper Hand will stop decaying for 20s. | K57: ouvrir | L57: ouvrir
A58: Gravity Tide Cap | B58: Gravity Tide | C58: Helmet | D58: Legendary | E58: 60 | F58: 21 | H58: 1p : Jump Height +10%. | 2p : Magazine Capacity Bonus 15%. | 3p : When airborne gain 20% monster DMG Reduction; for every 5 meters moved in the air, gain 1 stack of Upper Hand increasing Weapon and Status DMG by +1,5% up to a maximum of 15 stacks. Loose one stack of Upper Hand every 5s. | 4p : When Upper Hand exceeds 10 stacks, Weapon and Status damage +10%; After moving 30 meters in the air, Upper Hand will stop decaying for 20s. | K58: ouvrir | L58: ouvrir
A59: Gravity Tide Facewear | B59: Gravity Tide | C59: Mask | D59: Legendary | E59: 30 | F59: 28 | H59: 1p : Jump Height +10%. | 2p : Magazine Capacity Bonus 15%. | 3p : When airborne gain 20% monster DMG Reduction; for every 5 meters moved in the air, gain 1 stack of Upper Hand increasing Weapon and Status DMG by +1,5% up to a maximum of 15 stacks. Loose one stack of Upper Hand every 5s. | 4p : When Upper Hand exceeds 10 stacks, Weapon and Status damage +10%; After moving 30 meters in the air, Upper Hand will stop decaying for 20s. | K59: ouvrir | L59: ouvrir
A60: Gravity Tide Shoes | B60: Gravity Tide | C60: Shoes | D60: Legendary | E60: 120 | F60: 21 | H60: 1p : Jump Height +10%. | 2p : Magazine Capacity Bonus 15%. | 3p : When airborne gain 20% monster DMG Reduction; for every 5 meters moved in the air, gain 1 stack of Upper Hand increasing Weapon and Status DMG by +1,5% up to a maximum of 15 stacks. Loose one stack of Upper Hand every 5s. | 4p : When Upper Hand exceeds 10 stacks, Weapon and Status damage +10%; After moving 30 meters in the air, Upper Hand will stop decaying for 20s. | K60: ouvrir | L60: ouvrir
A61: Gravity Tide Top | B61: Gravity Tide | C61: Top | D61: Legendary | E61: 156 | F61: 28 | H61: 1p : Jump Height +10%. | 2p : Magazine Capacity Bonus 15%. | 3p : When airborne gain 20% monster DMG Reduction; for every 5 meters moved in the air, gain 1 stack of Upper Hand increasing Weapon and Status DMG by +1,5% up to a maximum of 15 stacks. Loose one stack of Upper Hand every 5s. | 4p : When Upper Hand exceeds 10 stacks, Weapon and Status damage +10%; After moving 30 meters in the air, Upper Hand will stop decaying for 20s. | K61: ouvrir | L61: ouvrir
A62: Heavy Duty Clothing Pants | B62: Heavy Duty | C62: Bottoms | D62: Epic | E62: 130 | F62: 21 | H62: 1p : Max HP +10.0%. | 2p : Element DMG (Blaze, Frost, Shock, Blast) + 8%. | 3p : After killing an enemy, increase Movement Speed by 20% for 2s and Elemental DMG (Blaze, Frost, Shock, Blast) by 40%, decay over 8s. | 4p : Within 5m, each enemy grants you DMG Reduction +4%. Effect can stack up to 4 times. | K62: ouvrir | L62: ouvrir
A63: Heavy Duty Clothing Gloves | B63: Heavy Duty | C63: Gloves | D63: Epic | E63: 81 | F63: 21 | H63: 1p : Max HP +10.0%. | 2p : Element DMG (Blaze, Frost, Shock, Blast) + 8%. | 3p : After killing an enemy, increase Movement Speed by 20% for 2s and Elemental DMG (Blaze, Frost, Shock, Blast) by 40%, decay over 8s. | 4p : Within 5m, each enemy grants you DMG Reduction +4%. Effect can stack up to 4 times. | K63: ouvrir | L63: ouvrir
A64: Heavy Duty Clothing Helmet | B64: Heavy Duty | C64: Helmet | D64: Epic | E64: 54 | F64: 21 | H64: 1p : Max HP +10.0%. | 2p : Element DMG (Blaze, Frost, Shock, Blast) + 8%. | 3p : After killing an enemy, increase Movement Speed by 20% for 2s and Elemental DMG (Blaze, Frost, Shock, Blast) by 40%, decay over 8s. | 4p : Within 5m, each enemy grants you DMG Reduction +4%. Effect can stack up to 4 times. | K64: ouvrir | L64: ouvrir
A65: Heavy Duty Clothing Mask | B65: Heavy Duty | C65: Mask | D65: Epic | E65: 27 | F65: 28 | H65: 1p : Max HP +10.0%. | 2p : Element DMG (Blaze, Frost, Shock, Blast) + 8%. | 3p : After killing an enemy, increase Movement Speed by 20% for 2s and Elemental DMG (Blaze, Frost, Shock, Blast) by 40%, decay over 8s. | 4p : Within 5m, each enemy grants you DMG Reduction +4%. Effect can stack up to 4 times. | K65: ouvrir | L65: ouvrir
A66: Heavy Duty Clothing Boots | B66: Heavy Duty | C66: Shoes | D66: Epic | E66: 108 | F66: 21 | H66: 1p : Max HP +10.0%. | 2p : Element DMG (Blaze, Frost, Shock, Blast) + 8%. | 3p : After killing an enemy, increase Movement Speed by 20% for 2s and Elemental DMG (Blaze, Frost, Shock, Blast) by 40%, decay over 8s. | 4p : Within 5m, each enemy grants you DMG Reduction +4%. Effect can stack up to 4 times. | K66: ouvrir | L66: ouvrir
A67: Heavy Duty Clothing Top | B67: Heavy Duty | C67: Top | D67: Epic | E67: 140 | F67: 28 | H67: 1p : Max HP +10.0%. | 2p : Element DMG (Blaze, Frost, Shock, Blast) + 8%. | 3p : After killing an enemy, increase Movement Speed by 20% for 2s and Elemental DMG (Blaze, Frost, Shock, Blast) by 40%, decay over 8s. | 4p : Within 5m, each enemy grants you DMG Reduction +4%. Effect can stack up to 4 times. | K67: ouvrir | L67: ouvrir
... A73: Lonewolf Jacket | B73: Lonewolf | C73: Top | D73: Legendary | E73: 156 | F73: 28 | H73: 1p : Magazine Capacity +10.0%. | 2p : Crit Rate +5.0%. | 3p : Get 1 stacks of Lone Shadow with every 2 weapon crit hit(s). Lone Shadow: Crit DMG + 6% for 30s. The effect can stack up to 8 times. | 4p : Increase max Lone Shadow stacks to 10. After a kill, Crit Rate +8% for 2s. | K73: ouvrir | L73: ouvrir
A74: Hot Dog Shorts | B74: Pièce unique | C74: Bottoms | D74: Epic | E74: 130 | F74: 21 | G74: Bounces +2 | K74: ouvrir | L74: ouvrir
A75: Overloaded Pants | B75: Pièce unique | C75: Bottoms | D75: Legendary | E75: 144 | F75: 21 | G75: After triggering Power Surge 20 times, the next 6 shots will consume reserve ammo instead and Shock DMG +20%. Cooldown: 4s. Triggering Power Surge during the cooldown does not count toward this effect. | K75: ouvrir | L75: ouvrir
A76: Sharp Blade Pants | B76: Pièce unique | C76: Bottoms | D76: Legendary | E76: 144 | F76: 21 | G76: When Triggering Bounce , additionally trigger 1 more time. | K76: ouvrir | L76: ouvrir
A77: Tattoo Pants | B77: Pièce unique | C77: Bottoms | D77: Legendary | E77: 144 | F77: 21 | G77: Bounce has a 100% chance to bounce again upon a hit, dealing 100% Bounce DMG. | K77: ouvrir | L77: ouvrir
A78: Glide Pants | B78: Pièce unique | C78: Bottoms | D78: Legendary | E78: 1770 | F78: 21 | G78: When not in an Unarmed State , replaces Roll with Slide. After sliding, Reload Efficiency +100% and Movement Speed + 30% for 2s. If you are holding a bow sliding immediately load 1 ammo and additionally increases Draw Speed by 100% for 1.5s. | K78: ouvrir
A79: Prickly Dance Pants | B79: Pièce unique | C79: Bottoms | D79: Legendary | E79: 1770 | F79: 21 | G79: Bounce has a 100% chance to bounce again upon a hit, dealing 100% Bounce DMG. | K79: ouvrir
A80: Test Subject Pants | B80: Pièce unique | C80: Bottoms | D80: Uncommon | E80: 1241 | F80: 21 | K80: ouvrir
A81: BBQ Grill Gloves | B81: Pièce unique | C81: Gloves | D81: Epic | E81: 81 | F81: 21 | G81: Burn damage frequency increases with the number of stacks, up to 100%. | K81: ouvrir | L81: ouvrir
A82: Drifter Gauntlets | B82: Pièce unique | C82: Gloves | D82: Legendary | E82: 90 | F82: 21 | G82: When affected by Burn, Weapon DMG +15% and Crit Rate +15%. | K82: ouvrir | L82: ouvrir
A83: Gilded Gloves | B83: Pièce unique | C83: Gloves | D83: Legendary | E83: 90 | F83: 21 | G83: Unlocks the Crit Hit Ability to Burn. (Can utilize Character Crit Rate). | K83: ouvrir | L83: ouvrir
A84: Hardy Gloves | B84: Pièce unique | C84: Gloves | D84: Legendary | E84: 90 | F84: 21 | G84: At full stack, Burn will cause an explosion that deals Blaze DMG of 300% Psi Intensity and remove all stacks of Burn. | K84: ouvrir | L84: ouvrir
A85: Snow Camo Gloves | B85: Pièce unique | C85: Gloves | D85: Legendary | E85: 90 | F85: 21 | G85: When an Ice Crystal shatters, 4 additional ice missile(s) will launch at nearby enemies, dealing Status DMG equal to 40% Psi Intensity to targets hit (60% DMG to players; Frost Vortex DMG bonus applies). | K85: ouvrir | L85: ouvrir
A86: Beret | B86: Pièce unique | C86: Helmet | D86: Epic | E86: 54 | F86: 21 | G86: Shrapnel Hit Part +1. | K86: ouvrir | L86: ouvrir
A87: Cage Helmet | B87: Pièce unique | C87: Helmet | D87: Legendary | E87: 60 | F87: 21 | G87: Shrapnel Trigger Count +1. | K87: ouvrir | L87: ouvrir
A88: Gas Mask Hood | B88: Pièce unique | C88: Helmet | D88: Legendary | E88: 60 | F88: 21 | G88: After trigger Power Surge, Crit Rate +35% for 3s. | K88: ouvrir | L88: ouvrir
A89: Gas-Tight Helmet | B89: Pièce unique | C89: Helmet | D89: Legendary | E89: 60 | F89: 21 | G89: Max Shrapnel target parts 1. Shrapnel DMG +120%. | K89: ouvrir | L89: ouvrir
A90: Mayfly Goggles | B90: Pièce unique | C90: Helmet | D90: Epic | E90: 54 | F90: 21 | G90: Power Surge Trigger count +1. Power Surge Damage -30%. | K90: ouvrir | L90: ouvrir
A91: Raid Face Shield | B91: Pièce unique | C91: Helmet | D91: Rare | E91: 48 | F91: 21 | K91: ouvrir | L91: ouvrir
A92: Yellow Pain Mask | B92: Pièce unique | C92: Helmet | D92: Legendary | E92: 60 | F92: 21 | G92: Defeating enemies will generate EMP, dealing Power Surge 1 time to enemies in the area. | K92: ouvrir | L92: ouvrir
A93: Wild Interpreter Cap | B93: Pièce unique | C93: Helmet | D93: Legendary | E93: 738 | F93: 21 | G93: When triggering Unstable Bomber auto-load 1 bullet. Unstable Bomber damage rate +25%. | K93: ouvrir
A94: Dust Mask | B94: Pièce unique | C94: Mask | D94: Legendary | E94: 30 | F94: 28 | G94: When triggering Fast Gunner, there is a 50% chance to automatically reload 1 bullet(s). | K94: ouvrir | L94: ouvrir
A95: Oasis Mask | B95: Pièce unique | C95: Mask | D95: Legendary | E95: 30 | F95: 28 | G95: Fast Gunner max stacks +10 Attack +1% per stack. | K95: ouvrir | L95: ouvrir
A96: Precise Shot Mask | B96: Pièce unique | C96: Mask | D96: Epic | E96: 27 | F96: 28 | G96: When triggering Fast Gunner, Reload Speed +25%, up to 10 stacks(s). Effect is removed after reloading after reloading or switching weapons. | K96: ouvrir | L96: ouvrir
A97: Viper Mask | B97: Pièce unique | C97: Mask | D97: Legendary | E97: 30 | F97: 28 | G97: Unstable Bomber range +50%. For every 2% increase in range, gain 1% more Unstable Bomber DMG. | K97: ouvrir | L97: ouvrir
A98: Ankh Mask | B98: Pièce unique | C98: Mask | D98: Legendary | E98: 246 | F98: 28 | G98: When the magazine is emptied, there's a 40% chance to consume reserve ammo and refill the magazine with 20% bullets (rounded down). | K98: ouvrir
A99: Test Subject Mask | B99: Pièce unique | C99: Mask | D99: Uncommon | E99: 258 | F99: 28 | K99: ouvrir
A100: Bloodstained Tracker Boots | B100: Pièce unique | C100: Shoes | D100: Legendary | E100: 120 | F100: 21 | G100: When Applying The Bull's Eye to an objective already marked by The Bull's Eye, your attack +20% for 5s, and The Bull's Eye spreads to one other nearby objective. | K100: ouvrir | L100: ouvrir
A101: Cowboy Boots | B101: Pièce unique | C101: Shoes | D101: Legendary | E101: 120 | F101: 21 | G101: Fortress Warfare only affects self. When in Fortress Warfare, Attack +25%. | K101: ouvrir | L101: ouvrir
A102: Earthly Boots | B102: Pièce unique | C102: Shoes | D102: Epic | E102: 108 | F102: 21 | G102: When hitting marked enemies, DMG +30%. | K102: ouvrir | L102: ouvrir
A103: Fire Rune Boots | B103: Pièce unique | C103: Shoes | D103: Legendary | E103: 120 | F103: 21 | G103: When any target nearby is inflicted with Burn, there's a 50% chance to generate a deviated particle. Picking it up increases Blaze DMG by 30% for 15s. | K103: ouvrir | L103: ouvrir
A104: Leather Boots | B104: Pièce unique | C104: Shoes | D104: Epic | E104: 108 | F104: 21 | G104: Recover 2.5% HP per second while in Fortress Warfare. Effects doubles when HP is below 50%. | K104: ouvrir | L104: ouvrir
A105: Old Huntsman Boots | B105: Pièce unique | C105: Shoes | D105: Legendary | E105: 120 | F105: 21 | G105: After triggering The Bull's Eye, the 1 bullet(s) hitting a marked target will count as Weakspot hits even if they do not hit the Weakspot. Weakspot DMG +30% to enemies affected by The Bull's Eye. | K105: ouvrir | L105: ouvrir
A106: Pivot Step Leather Boots | B106: Pièce unique | C106: Shoes | D106: Legendary | E106: 120 | F106: 21 | G106: Resets Battle Skill Cooldown after using Deviation Ultimate. | K106: ouvrir | L106: ouvrir
A107: Hard Tactical Boots | B107: Pièce unique | C107: Shoes | D107: Legendary | E107: 120 | F107: 21 | G107: Automatically refill 1 bullet(s) and increase Fire Rate by 15% when in Fortress Warfare. | K107: ouvrir | L107: ouvrir
A108: Tactical Combat Shoes | B108: Pièce unique | C108: Shoes | D108: Legendary | E108: 120 | F108: 21 | G108: When hitting marked enemies, there is a 40% to automatically reload 1 ammo and recover 1% of lost HP. | K108: ouvrir | L108: ouvrir
A109: Seasoned Hunter Leather Boots | B109: Pièce unique | C109: Shoes | D109: Legendary | E109: 1475 | F109: 21 | G109: After triggering The Bull's Eye, the next 1 bullet(s) will count as Weakspot hits even if they do not hit the Weakspot. Weakspot DMG +30% to enemies affected by The Bull's Eye. | K109: ouvrir
A110: Charmed Mag Top | B110: Pièce unique | C110: Top | D110: Legendary | E110: 156 | F110: 28 | G110: When the player is in Fast Gunner status, the less ammo or magazine capacity they have, the higher their chance of triggering an extra bullet when firing. At 1% ammo, the chance of triggering an extra bullet is 40%. | K110: ouvrir | L110: ouvrir
A111: Stealth Walker Wrap | B111: Pièce unique | C111: Top | D111: Legendary | E111: 156 | F111: 28 | G111: Frost Vortex collapsed in the center and keep pulling in 120% of enemies within Frost Vortex. | K111: ouvrir | L111: ouvrir
A112: Doyen's Cloak | B112: Pièce unique | C112: Top | D112: Legendary | E112: 156 | F112: 28 | G112: When the Frozen effect ends, deal Frost DMG equal to the 50 of the total damage you dealt to the target during the Frozen period. | K112: ouvrir | L112: ouvrir
A113: Explosive Front Top | B113: Pièce unique | C113: Top | D113: Legendary | E113: 156 | F113: 28 | G113: Unstable Bomber delay +0.3s. Unstable Bomber DMG +30%. | K113: ouvrir | L113: ouvrir
A114: Frost Tactical Vest | B114: Pièce unique | C114: Top | D114: Epic | E114: 140 | F114: 28 | G114: Frost Vortex generates Ice Spikes that deal Frost DMG of 100% Psi Intensity | K114: ouvrir | L114: ouvrir
A115: Sleek Leather Jacket | B115: Pièce unique | C115: Top | D115: Epic | E115: 140 | F115: 28 | G115: For every 1m Unstable Bomber is away from the player, Unstable Bomber Final DMG +2% | K115: ouvrir | L115: ouvrir
A116: Snowdrift Top | B116: Pièce unique | C116: Top | D116: Legendary | E116: 156 | F116: 28 | G116: • When picking up Deviant Particles, gains an additional charge stack, and Weapon and Status DMG+25% for 25s. | K116: ouvrir | L116: ouvrir
A117: Magnetic Moment Top | B117: Pièce unique | C117: Top | D117: Legendary | E117: 1918 | F117: 28 | G117: Targets affected by Power Surge continously pull in other enemy units within a 7m radius. | K117: ouvrir
A118: Shaman Vulture Top | B118: Pièce unique | C118: Top | D118: Legendary | E118: 1918 | F118: 28 | G118: After triggering Unstable Bomber, Crit Rate +35% for 3s. After triggering Unstable Bomber, Crit Rate +35% for 3s. | K118: ouvrir
A119: Test Subject Top | B119: Pièce unique | C119: Top | D119: Uncommon | E119: 1340 | F119: 28 | K119: ouvrir
A120: Raid Pants | B120: Raid | C120: Bottoms | D120: Rare | E120: 115 | F120: 21 | H120: 1p : Gathering Speed +15%. | 2p : Max Load +20. | 3p : When the load is over 80, DMG taken -10%, Weapon and Tactical Item DMG +20%. | 4p : Stamina cost -30% when gliding and rolling. | K120: ouvrir | L120: ouvrir
A121: Raid Gloves | B121: Raid | C121: Gloves | D121: Rare | E121: 72 | F121: 21 | H121: 1p : Gathering Speed +15%. | 2p : Max Load +20. | 3p : When the load is over 80, DMG taken -10%, Weapon and Tactical Item DMG +20%. | 4p : Stamina cost -30% when gliding and rolling. | K121: ouvrir | L121: ouvrir
A122: Raid Mask | B122: Raid | C122: Mask | D122: Rare | E122: 24 | F122: 28 | H122: 1p : Gathering Speed +15%. | 2p : Max Load +20. | 3p : When the load is over 80, DMG taken -10%, Weapon and Tactical Item DMG +20%. | 4p : Stamina cost -30% when gliding and rolling. | K122: ouvrir | L122: ouvrir
A123: Raid Shoes | B123: Raid | C123: Shoes | D123: Rare | E123: 96 | F123: 21 | H123: 1p : Gathering Speed +15%. | 2p : Max Load +20. | 3p : When the load is over 80, DMG taken -10%, Weapon and Tactical Item DMG +20%. | 4p : Stamina cost -30% when gliding and rolling. | K123: ouvrir | L123: ouvrir
A124: Raid Top | B124: Raid | C124: Top | D124: Rare | E124: 125 | F124: 28 | H124: 1p : Gathering Speed +15%. | 2p : Max Load +20. | 3p : When the load is over 80, DMG taken -10%, Weapon and Tactical Item DMG +20%. | 4p : Stamina cost -30% when gliding and rolling. | K124: ouvrir | L124: ouvrir
A125: Renegade Pants | B125: Renegade | C125: Bottoms | D125: Legendary | E125: 144 | F125: 21 | H125: 1p : Reload Speed +15.0%. | 2p : Weakspot DMG +10.0%. | 3p : Hitting the same enemy consecutively grants 1 stack of Archer's Focus, increasing Weakspot DMG by 4%, up to 10 stacks. Archer's Focus stacks are halved when the target is changed. | 4p : When reloading, for every 1% of weakspot hit from the previous magazine, load an extra 0.6% bullets, up to 30%. | K125: ouvrir | L125: ouvrir
A126: Renegade Gloves | B126: Renegade | C126: Gloves | D126: Legendary | E126: 90 | F126: 21 | H126: 1p : Reload Speed +15.0%. | 2p : Weakspot DMG +10.0%. | 3p : Hitting the same enemy consecutively grants 1 stack of Archer's Focus, increasing Weakspot DMG by 4%, up to 10 stacks. Archer's Focus stacks are halved when the target is changed. | 4p : When reloading, for every 1% of weakspot hit from the previous magazine, load an extra 0.6% bullets, up to 30%. | K126: ouvrir | L126: ouvrir
A127: Renegade Hood | B127: Renegade | C127: Helmet | D127: Legendary | E127: 60 | F127: 21 | H127: 1p : Reload Speed +15.0%. | 2p : Weakspot DMG +10.0%. | 3p : Hitting the same enemy consecutively grants 1 stack of Archer's Focus, increasing Weakspot DMG by 4%, up to 10 stacks. Archer's Focus stacks are halved when the target is changed. | 4p : When reloading, for every 1% of weakspot hit from the previous magazine, load an extra 0.6% bullets, up to 30%. | K127: ouvrir | L127: ouvrir
A128: Renegade Mask | B128: Renegade | C128: Mask | D128: Legendary | E128: 30 | F128: 28 | H128: 1p : Reload Speed +15.0%. | 2p : Weakspot DMG +10.0%. | 3p : Hitting the same enemy consecutively grants 1 stack of Archer's Focus, increasing Weakspot DMG by 4%, up to 10 stacks. Archer's Focus stacks are halved when the target is changed. | 4p : When reloading, for every 1% of weakspot hit from the previous magazine, load an extra 0.6% bullets, up to 30%. | K128: ouvrir | L128: ouvrir
A129: Renegade Shoes | B129: Renegade | C129: Shoes | D129: Legendary | E129: 120 | F129: 21 | H129: 1p : Reload Speed +15.0%. | 2p : Weakspot DMG +10.0%. | 3p : Hitting the same enemy consecutively grants 1 stack of Archer's Focus, increasing Weakspot DMG by 4%, up to 10 stacks. Archer's Focus stacks are halved when the target is changed. | 4p : When reloading, for every 1% of weakspot hit from the previous magazine, load an extra 0.6% bullets, up to 30%. | K129: ouvrir | L129: ouvrir
A130: Renegade Jacket | B130: Renegade | C130: Top | D130: Legendary | E130: 156 | F130: 28 | H130: 1p : Reload Speed +15.0%. | 2p : Weakspot DMG +10.0%. | 3p : Hitting the same enemy consecutively grants 1 stack of Archer's Focus, increasing Weakspot DMG by 4%, up to 10 stacks. Archer's Focus stacks are halved when the target is changed. | 4p : When reloading, for every 1% of weakspot hit from the previous magazine, load an extra 0.6% bullets, up to 30%. | K130: ouvrir | L130: ouvrir
A131: Rustic Pants | B131: Rustic | C131: Bottoms | D131: Uncommon | E131: 101 | F131: 21 | H131: 1p : Movement Speed +8.0%. | 2p : Melee Damage +15.0%. | 3p : HP +600. | 4p : Gathering Speed +20%. | K131: ouvrir | L131: ouvrir
... A176: Treacherous Tides Top | B176: Treacherous Tides | C176: Top | D176: Legendary | E176: 156 | F176: 28 | H176: 1p : Weapon DMG reduction 10%. | 2p : When HP is above 70%, Weapon DMG and Status DMG +12%. | 3p : The HP reduction from low Sanity is reduced by 40%. Weapon and Status DMG +10% and further increases as your Sanity drops up to 28% (at 30% Sanity) max. | 4p : Generates a shield equal to 20% of max HP when HP is below 40%. Cooldown: 8s. | K176: ouvrir | L176: ouvrir

Sheet Sets
A1: Set | B1: Rarity | C1: Pieces | D1: 1 piece | E1: 2 pieces | F1: 3 pieces | G1: 4 pieces | H1: Piece list
A2: Agent | B2: Epic | C2: 6 | D2: Head DMG Reduction +10.0%. | E2: Weakspot DMG +10.0%. | F2: Get Bullet Saver effect with every precise kill, Weakspot DMG +15% for 8s. Effect can stack up to 3 times. | G2: Increase Reload Speed by 20% after killing an enemy; Fire Rate +10% when killing with a Weakspot hit. Effect removed when reloading or switching weapons. | H2: Agent Gloves, Agent Helmet, Agent Mask, Agent Pants, Agent Shoes, Agent Top
A3: Bastille | B3: Legendary | C3: 6 | D3: When HP is above 70%, Weapon DMG +10%. | E3: Reload Speed +20.0%. | F3: Stay crouched and immobile for 0.5 seconds to enter Bastille state, which grants +40% Weapon DMG. Upon exiting Bastille state, sprinting is disabled for 3 seconds and C stamina consumption is increased by 100%. | G3: 3s after exiting Bastille state, gain 1 stack of Armor per second, up to 60 stacks. While in Bastille state, each stack of Armor provides a Shield equal to 1% of max HP. If the shield drops to 0 during Bastille state, you gain a 30% Vulnerability effect. | H3: Bastille Shoes, Bastille Gloves, Bastille Helmet, Bastille Mask, Bastille Pants, Bastille Jacket
A4: Blackstone | B4: Legendary | C4: 6 | D4: Cold and Heat Resist +2,5. | E4: Upon dealing Elemental DMG, gain 1 stack(s) of Warm Sensation (Elemental DMG +2%) for 2s. Triggers 1 time every 0.5s, up to a maximum of 5 stack(s). | F4: When the temperature is between 10 and 30, you gain the Warm status (Elemental DMG +18%). | G4: At 5 stacks of Warm Sensation, you are considered to be in the Warm status. When the environmental temperature is between 10C and 30C, gain Elemental DMG +7%. | H4: Blackstone Shoes, Blackstone Gloves, Blackstone Helmet, Blackstone Mask, Blackstone Pants, Blackstone Tops
A5: Blackstone (Cold) | B5: Legendary | C5: 6 | D5: Cold Resist +5 | E5: Upon dealing Elemental DMG, gain 1 stack of Warm Sensation (Elemental DMG +2%) for 2s. Triggers once every 0.5s, up to 5 stacks. | F5: When the temperature is below 10°C, gain Cold status (Elemental DMG +10%). For every additional degree below, Elemental DMG +0.5%, up to 20%. | G5: At 5 stacks of Warm Sensation, the environmental temperature drops by 5°C, the Cold status DMG bonus is doubled and its cap raised to 40%. | H5: Blackstone Boots - Cold, Blackstone Gloves - Cold, Blackstone Hood - Cold, Blackstone Mask - Cold, Blackstone Pants - Cold, Blackstone Top - Cold
A6: Blackstone (Heat) | B6: Legendary | C6: 6 | D6: Heat Resist +5 | E6: Upon dealing Elemental DMG, gain 1 stack of Warm Sensation (Elemental DMG +2%) for 2s. Triggers once every 0.5s, up to 5 stacks. | F6: When the temperature is above 30°C, gain Passion status (Elemental DMG +10%). For every additional degree above, Elemental DMG +0.5%, up to 20%. | G6: At 5 stacks of Warm Sensation, the environmental temperature rises by 5°C, the Passion status DMG bonus is doubled and its cap raised to 40%. | H6: Blackstone Boots - Heat, Blackstone Gloves - Heat, Blackstone Hood - Heat, Blackstone Mask - Heat, Blackstone Pants - Heat, Blackstone Top - Heat
A7: Blast | B7: Rare | C7: 6 | D7: Heavy Melee DMG +20%. | E7: Torso DMG Reduction +12.0%. | F7: After killing an enemy with a melee attack. DMG +25% for next melee attack within 5s, Melee Swing Speed +15%. | G7: Melee kill an enemy to instantly recover 30 Stamina and increase Movement Speed by 20% for 2s (cooldown: 3s). | H7: Blast Gloves, Blast Helmet, Blast Mask, Blast Pants, Blast Shoes, Blast Top
A8: Dark Resonance | B8: Legendary | C8: 6 | D8: Using ultimate grants 10% temporary shield for 10 seconds. | E8: When Deviant Power is not full, Weapon and Status DMG +12%. | F8: Fr every 1 Energy consumed, Gun and Status DMG +0,6% up to +30%. | G8: Consumes 30 Deviant Power when using Battle Skill, reduces Cooldown by 50%. | H8: Dark Resonance Gloves, Dark Resonance Helmet, Dark Resonance Mask, Dark Resonance Pants, Dark Resonance Shoes, Dark Resonance Vest
A9: Falcon | B9: Epic | C9: 6 | D9: Rolling Stamina cost -20%. | E9: Crit DMG +12.0%. | F9: When Stamina is over 90%, increase Crit Rate by 5% and Crit DMG by 20%. | G9: Max Stamina +25. Recover 30 Stamina instantly with a kill. | H9: Falcon Helmet, Falcon Gloves, Falcon Jacket, Falcon Mask, Falcon Pants, Falcon Shoes
A10: Ghost Link | B10: Legendary | C10: 6 | D10: Increases Crit Rate by 3%. | E10: Reload Efficiency +15%. | F10: When dealing Weapon DMG, you gain 1 stack of Sync: Weapon DMG +3%. Stacks up to 10 times. Last 5s. | G10: When Sync reaches 10 stacks, attacking an enemy applies Overload. Overload: Deals Status DMG equal to 50% of Psi Intensity every second to the target and enemies within 3m. Last 5s. | H10: Ghost Link Gloves, Ghost Link Helmet, Ghost Link Mask, Ghost Link Pants, Ghost Link Shoes, Ghost Link Vest
A11: Gravity Tide | B11: Legendary | C11: 6 | D11: Jump Height +10%. | E11: Magazine Capacity Bonus 15%. | F11: When airborne gain 20% monster DMG Reduction; for every 5 meters moved in the air, gain 1 stack of Upper Hand increasing Weapon and Status DMG by +1,5% up to a maximum of 15 stacks. Loose one stack of Upper Hand every 5s. | G11: When Upper Hand exceeds 10 stacks, Weapon and Status damage +10%; After moving 30 meters in the air, Upper Hand will stop decaying for 20s. | H11: Gravity Tide Cap, Gravity Tide Facewear, Gravity Tide Gloves, Gravity Tide Pants, Gravity Tide Shoes, Gravity Tide Top
A12: Heavy Duty | B12: Epic | C12: 6 | D12: Max HP +10.0%. | E12: Element DMG (Blaze, Frost, Shock, Blast) + 8%. | F12: After killing an enemy, increase Movement Speed by 20% for 2s and Elemental DMG (Blaze, Frost, Shock, Blast) by 40%, decay over 8s. | G12: Within 5m, each enemy grants you DMG Reduction +4%. Effect can stack up to 4 times. | H12: Heavy Duty Clothing Gloves, Heavy Duty Clothing Helmet, Heavy Duty Clothing Mask, Heavy Duty Clothing Pants, Heavy Duty Clothing Boots, Heavy Duty Clothing Top
A13: Lonewolf | B13: Legendary | C13: 6 | D13: Magazine Capacity +10.0%. | E13: Crit Rate +5.0%. | F13: Get 1 stacks of Lone Shadow with every 2 weapon crit hit(s). Lone Shadow: Crit DMG + 6% for 30s. The effect can stack up to 8 times. | G13: Increase max Lone Shadow stacks to 10. After a kill, Crit Rate +8% for 2s. | H13: Lonewolf Gloves, Lonewolf Hat, Lonewolf Jacket, Lonewolf Mask, Lonewolf Pants, Lonewolf Shoes
... A23: Treacherous Tides | B23: Legendary | C23: 6 | D23: Weapon DMG reduction 10%. | E23: When HP is above 70%, Weapon DMG and Status DMG +12%. | F23: The HP reduction from low Sanity is reduced by 40%. Weapon and Status DMG +10% and further increases as your Sanity drops up to 28% (at 30% Sanity) max. | G23: Generates a shield equal to 20% of max HP when HP is below 40%. Cooldown: 8s. | H23: Treacherous Tides Gloves, Treacherous Tides Helmet, Treacherous Tides Mask, Treacherous Tides Pants, Treacherous Tides Shoes, Treacherous Tides Top

Sheet Mods
A1: Name <Variant> | B1: Name | C1: Category | D1: Slot | E1: Variant | F1: Main effect | G1: Page | H1: Image
A2: Abnormal Increase <Aero> | B2: Abnormal Increase | C2: Armor Mod | D2: Bottoms | E2: Aero | F2: When the magazine is empty, Status DMG +10% for 12s (up to 3 stacks). | G2: ouvrir
A3: Abnormal Increase <Aero Deviant Energy> | B3: Abnormal Increase | C3: Armor Mod | D3: Bottoms | E3: Aero Deviant Energy | F3: When the magazine is empty, Status DMG +10% for 12s (up to 3 stacks). | G3: ouvrir
A4: Abnormal Increase <Deviant Energy> | B4: Abnormal Increase | C4: Armor Mod | D4: Bottoms | E4: Deviant Energy | F4: When the magazine is empty, Status DMG +10% for 12s (up to 3 stacks). | G4: ouvrir
A5: Abnormal Increase <Downstar> | B5: Abnormal Increase | C5: Armor Mod | D5: Bottoms | E5: Downstar | F5: When the magazine is empty, Status DMG +10% for 12s (up to 3 stacks). | G5: ouvrir
A6: Abnormal Increase <Downstar Deviant Energy> | B6: Abnormal Increase | C6: Armor Mod | D6: Bottoms | E6: Downstar Deviant Energy | F6: When the magazine is empty, Status DMG +10% for 12s (up to 3 stacks). | G6: ouvrir
A7: Abnormal Increase <General> | B7: Abnormal Increase | C7: Armor Mod | D7: Bottoms | E7: General | F7: When the magazine is empty, Status DMG +10% for 12s (up to 3 stacks). | G7: ouvrir
A8: Abnormal Increase <Precision> | B8: Abnormal Increase | C8: Armor Mod | D8: Bottoms | E8: Precision | F8: When the magazine is empty, Status DMG +10% for 12s (up to 3 stacks). | G8: ouvrir
A9: Abnormal Increase <Resonance> | B9: Abnormal Increase | C9: Armor Mod | D9: Bottoms | E9: Resonance | F9: When the magazine is empty, Status DMG +10% for 12s (up to 3 stacks). | G9: ouvrir
A10: Abnormal Increase <Resonance Deviant Energy> | B10: Abnormal Increase | C10: Armor Mod | D10: Bottoms | E10: Resonance Deviant Energy | F10: When the magazine is empty, Status DMG +10% for 12s (up to 3 stacks). | G10: ouvrir
A11: Abnormal Increase <Survival> | B11: Abnormal Increase | C11: Armor Mod | D11: Bottoms | E11: Survival | F11: When the magazine is empty, Status DMG +10% for 12s (up to 3 stacks). | G11: ouvrir
A12: Abnormal Increase <Violent> | B12: Abnormal Increase | C12: Armor Mod | D12: Bottoms | E12: Violent | F12: When the magazine is empty, Status DMG +10% for 12s (up to 3 stacks). | G12: ouvrir
A13: Bullet Siphon <Aero> | B13: Bullet Siphon | C13: Armor Mod | D13: Bottoms | E13: Aero | F13: Weapon DMG +5%. Every 5 bullets consumed in the magazine grants +4% Weapon DMG, capped at 20%. | G13: ouvrir
A14: Bullet Siphon <Aero Deviant Energy> | B14: Bullet Siphon | C14: Armor Mod | D14: Bottoms | E14: Aero Deviant Energy | F14: Weapon DMG +5%. Every 5 bullets consumed in the magazine grants +4% Weapon DMG, capped at 20%. | G14: ouvrir
A15: Bullet Siphon <Deviant Energy> | B15: Bullet Siphon | C15: Armor Mod | D15: Bottoms | E15: Deviant Energy | F15: Weapon DMG +5%. Every 5 bullets consumed in the magazine grants +4% Weapon DMG, capped at 20%. | G15: ouvrir | H15: ouvrir
A16: Bullet Siphon <Downstar> | B16: Bullet Siphon | C16: Armor Mod | D16: Bottoms | E16: Downstar | F16: Weapon DMG +5%. Every 5 bullets consumed in the magazine grants +4% Weapon DMG, capped at 20%. | G16: ouvrir | H16: ouvrir
A17: Bullet Siphon <Downstar Deviant Energy> | B17: Bullet Siphon | C17: Armor Mod | D17: Bottoms | E17: Downstar Deviant Energy | F17: Weapon DMG +5%. Every 5 bullets consumed in the magazine grants +4% Weapon DMG, capped at 20%. | G17: ouvrir | H17: ouvrir
A18: Bullet Siphon <General> | B18: Bullet Siphon | C18: Armor Mod | D18: Bottoms | E18: General | F18: Weapon DMG +5%. Every 5 bullets consumed in the magazine grants +4% Weapon DMG, capped at 20%. | G18: ouvrir | H18: ouvrir
A19: Bullet Siphon <Precision> | B19: Bullet Siphon | C19: Armor Mod | D19: Bottoms | E19: Precision | F19: Weapon DMG +5%. Every 5 bullets consumed in the magazine grants +4% Weapon DMG, capped at 20%. | G19: ouvrir | H19: ouvrir
A20: Bullet Siphon <Resonance> | B20: Bullet Siphon | C20: Armor Mod | D20: Bottoms | E20: Resonance | F20: Weapon DMG +5%. Every 5 bullets consumed in the magazine grants +4% Weapon DMG, capped at 20%. | G20: ouvrir | H20: ouvrir
A21: Bullet Siphon <Resonance Deviant Energy> | B21: Bullet Siphon | C21: Armor Mod | D21: Bottoms | E21: Resonance Deviant Energy | F21: Weapon DMG +5%. Every 5 bullets consumed in the magazine grants +4% Weapon DMG, capped at 20%. | G21: ouvrir | H21: ouvrir
A22: Bullet Siphon <Survival> | B22: Bullet Siphon | C22: Armor Mod | D22: Bottoms | E22: Survival | F22: Weapon DMG +5%. Every 5 bullets consumed in the magazine grants +4% Weapon DMG, capped at 20%. | G22: ouvrir | H22: ouvrir
A23: Bullet Siphon <Violent> | B23: Bullet Siphon | C23: Armor Mod | D23: Bottoms | E23: Violent | F23: Weapon DMG +5%. Every 5 bullets consumed in the magazine grants +4% Weapon DMG, capped at 20%. | G23: ouvrir | H23: ouvrir
A24: Critical Surge <Aero> | B24: Critical Surge | C24: Armor Mod | D24: Bottoms | E24: Aero | F24: When the magazine is empty, gain Crit DMG for 12s; the effect can stack independently up to 3 times. | G24: ouvrir
A25: Critical Surge <Aero Deviant Energy> | B25: Critical Surge | C25: Armor Mod | D25: Bottoms | E25: Aero Deviant Energy | F25: When the magazine is empty, gain Crit DMG for 12s; the effect can stack independently up to 3 times. | G25: ouvrir
A26: Critical Surge <Deviant Energy> | B26: Critical Surge | C26: Armor Mod | D26: Bottoms | E26: Deviant Energy | F26: When the magazine is empty, gain Crit DMG for 12s; the effect can stack independently up to 3 times. | G26: ouvrir | H26: ouvrir
A27: Critical Surge <Downstar> | B27: Critical Surge | C27: Armor Mod | D27: Bottoms | E27: Downstar | F27: When the magazine is empty, gain Crit DMG for 12s; the effect can stack independently up to 3 times. | G27: ouvrir | H27: ouvrir
A28: Critical Surge <Downstar Deviant Energy> | B28: Critical Surge | C28: Armor Mod | D28: Bottoms | E28: Downstar Deviant Energy | F28: When the magazine is empty, gain Crit DMG for 12s; the effect can stack independently up to 3 times. | G28: ouvrir | H28: ouvrir
A29: Critical Surge <General> | B29: Critical Surge | C29: Armor Mod | D29: Bottoms | E29: General | F29: When the magazine is empty, gain Crit DMG for 12s; the effect can stack independently up to 3 times. | G29: ouvrir | H29: ouvrir
A30: Critical Surge <Precision> | B30: Critical Surge | C30: Armor Mod | D30: Bottoms | E30: Precision | F30: When the magazine is empty, gain Crit DMG for 12s; the effect can stack independently up to 3 times. | G30: ouvrir | H30: ouvrir
A31: Critical Surge <Resonance> | B31: Critical Surge | C31: Armor Mod | D31: Bottoms | E31: Resonance | F31: When the magazine is empty, gain Crit DMG for 12s; the effect can stack independently up to 3 times. | G31: ouvrir | H31: ouvrir
A32: Critical Surge <Resonance Deviant Energy> | B32: Critical Surge | C32: Armor Mod | D32: Bottoms | E32: Resonance Deviant Energy | F32: When the magazine is empty, gain Crit DMG for 12s; the effect can stack independently up to 3 times. | G32: ouvrir | H32: ouvrir
A33: Critical Surge <Survival> | B33: Critical Surge | C33: Armor Mod | D33: Bottoms | E33: Survival | F33: When the magazine is empty, gain Crit DMG for 12s; the effect can stack independently up to 3 times. | G33: ouvrir | H33: ouvrir
A34: Critical Surge <Violent> | B34: Critical Surge | C34: Armor Mod | D34: Bottoms | E34: Violent | F34: When the magazine is empty, gain Crit DMG for 12s; the effect can stack independently up to 3 times. | G34: ouvrir | H34: ouvrir
A35: Deadshot <Aero> | B35: Deadshot | C35: Armor Mod | D35: Bottoms | E35: Aero | F35: Each Crit Hit by non-melee weapons grants +5% Crit DMG, up to 45%. The effect is removed upon the next reload. | G35: ouvrir
A36: Deadshot <Aero Deviant Energy> | B36: Deadshot | C36: Armor Mod | D36: Bottoms | E36: Aero Deviant Energy | F36: Each Crit Hit by non-melee weapons grants +5% Crit DMG, up to 45%. The effect is removed upon the next reload. | G36: ouvrir
A37: Deadshot <Deviant Energy> | B37: Deadshot | C37: Armor Mod | D37: Bottoms | E37: Deviant Energy | F37: Each Crit Hit by non-melee weapons grants +5% Crit DMG, up to 45%. The effect is removed upon the next reload. | G37: ouvrir | H37: ouvrir
A38: Deadshot <Downstar> | B38: Deadshot | C38: Armor Mod | D38: Bottoms | E38: Downstar | F38: Each Crit Hit by non-melee weapons grants +5% Crit DMG, up to 45%. The effect is removed upon the next reload. | G38: ouvrir | H38: ouvrir
A39: Deadshot <Downstar Deviant Energy> | B39: Deadshot | C39: Armor Mod | D39: Bottoms | E39: Downstar Deviant Energy | F39: Each Crit Hit by non-melee weapons grants +5% Crit DMG, up to 45%. The effect is removed upon the next reload. | G39: ouvrir | H39: ouvrir
A40: Deadshot <General> | B40: Deadshot | C40: Armor Mod | D40: Bottoms | E40: General | F40: Each Crit Hit by non-melee weapons grants +5% Crit DMG, up to 45%. The effect is removed upon the next reload. | G40: ouvrir | H40: ouvrir
A41: Deadshot <Precision> | B41: Deadshot | C41: Armor Mod | D41: Bottoms | E41: Precision | F41: Each Crit Hit by non-melee weapons grants +5% Crit DMG, up to 45%. The effect is removed upon the next reload. | G41: ouvrir | H41: ouvrir
A42: Deadshot <Resonance> | B42: Deadshot | C42: Armor Mod | D42: Bottoms | E42: Resonance | F42: Each Crit Hit by non-melee weapons grants +5% Crit DMG, up to 45%. The effect is removed upon the next reload. | G42: ouvrir | H42: ouvrir
A43: Deadshot <Resonance Deviant Energy> | B43: Deadshot | C43: Armor Mod | D43: Bottoms | E43: Resonance Deviant Energy | F43: Each Crit Hit by non-melee weapons grants +5% Crit DMG, up to 45%. The effect is removed upon the next reload. | G43: ouvrir | H43: ouvrir
A44: Deadshot <Survival> | B44: Deadshot | C44: Armor Mod | D44: Bottoms | E44: Survival | F44: Each Crit Hit by non-melee weapons grants +5% Crit DMG, up to 45%. The effect is removed upon the next reload. | G44: ouvrir | H44: ouvrir
A45: Deadshot <Violent> | B45: Deadshot | C45: Armor Mod | D45: Bottoms | E45: Violent | F45: Each Crit Hit by non-melee weapons grants +5% Crit DMG, up to 45%. The effect is removed upon the next reload. | G45: ouvrir | H45: ouvrir
A46: Distant Strike <Aero> | B46: Distant Strike | C46: Armor Mod | D46: Bottoms | E46: Aero | F46: Weakspot DMG increases against targets beyond 20m and scales further with distance, up to its cap. | G46: ouvrir
A47: Distant Strike <Aero Deviant Energy> | B47: Distant Strike | C47: Armor Mod | D47: Bottoms | E47: Aero Deviant Energy | F47: Weakspot DMG increases against targets beyond 20m and scales further with distance, up to its cap. | G47: ouvrir
A48: Distant Strike <Deviant Energy> | B48: Distant Strike | C48: Armor Mod | D48: Bottoms | E48: Deviant Energy | F48: Weakspot DMG increases against targets beyond 20m and scales further with distance, up to its cap. | G48: ouvrir | H48: ouvrir
A49: Distant Strike <Downstar> | B49: Distant Strike | C49: Armor Mod | D49: Bottoms | E49: Downstar | F49: Weakspot DMG increases against targets beyond 20m and scales further with distance, up to its cap. | G49: ouvrir | H49: ouvrir
A50: Distant Strike <Downstar Deviant Energy> | B50: Distant Strike | C50: Armor Mod | D50: Bottoms | E50: Downstar Deviant Energy | F50: Weakspot DMG increases against targets beyond 20m and scales further with distance, up to its cap. | G50: ouvrir | H50: ouvrir
A51: Distant Strike <General> | B51: Distant Strike | C51: Armor Mod | D51: Bottoms | E51: General | F51: Weakspot DMG increases against targets beyond 20m and scales further with distance, up to its cap. | G51: ouvrir | H51: ouvrir
A52: Distant Strike <Precision> | B52: Distant Strike | C52: Armor Mod | D52: Bottoms | E52: Precision | F52: Weakspot DMG increases against targets beyond 20m and scales further with distance, up to its cap. | G52: ouvrir | H52: ouvrir
A53: Distant Strike <Resonance> | B53: Distant Strike | C53: Armor Mod | D53: Bottoms | E53: Resonance | F53: Weakspot DMG increases against targets beyond 20m and scales further with distance, up to its cap. | G53: ouvrir | H53: ouvrir
A54: Distant Strike <Resonance Deviant Energy> | B54: Distant Strike | C54: Armor Mod | D54: Bottoms | E54: Resonance Deviant Energy | F54: Weakspot DMG increases against targets beyond 20m and scales further with distance, up to its cap. | G54: ouvrir | H54: ouvrir
A55: Distant Strike <Survival> | B55: Distant Strike | C55: Armor Mod | D55: Bottoms | E55: Survival | F55: Weakspot DMG increases against targets beyond 20m and scales further with distance, up to its cap. | G55: ouvrir | H55: ouvrir
A56: Distant Strike <Violent> | B56: Distant Strike | C56: Armor Mod | D56: Bottoms | E56: Violent | F56: Weakspot DMG increases against targets beyond 20m and scales further with distance, up to its cap. | G56: ouvrir | H56: ouvrir
A57: Elemental Resonance <Aero> | B57: Elemental Resonance | C57: Armor Mod | D57: Bottoms | E57: Aero | F57: For each instance of Elemental DMG dealt from the previous magazine, the next magazine gains Elemental DMG +1% for 15s upon reloading, up to +24%. | G57: ouvrir
A58: Elemental Resonance <Aero Deviant Energy> | B58: Elemental Resonance | C58: Armor Mod | D58: Bottoms | E58: Aero Deviant Energy | F58: For each instance of Elemental DMG dealt from the previous magazine, the next magazine gains Elemental DMG +1% for 15s upon reloading, up to +24%. | G58: ouvrir
A59: Elemental Resonance <Deviant Energy> | B59: Elemental Resonance | C59: Armor Mod | D59: Bottoms | E59: Deviant Energy | F59: For each instance of Elemental DMG dealt from the previous magazine, the next magazine gains Elemental DMG +1% for 15s upon reloading, up to +24%. | G59: ouvrir | H59: ouvrir
A60: Elemental Resonance <Downstar> | B60: Elemental Resonance | C60: Armor Mod | D60: Bottoms | E60: Downstar | F60: For each instance of Elemental DMG dealt from the previous magazine, the next magazine gains Elemental DMG +1% for 15s upon reloading, up to +24%. | G60: ouvrir | H60: ouvrir
A61: Elemental Resonance <Downstar Deviant Energy> | B61: Elemental Resonance | C61: Armor Mod | D61: Bottoms | E61: Downstar Deviant Energy | F61: For each instance of Elemental DMG dealt from the previous magazine, the next magazine gains Elemental DMG +1% for 15s upon reloading, up to +24%. | G61: ouvrir | H61: ouvrir
A62: Elemental Resonance <General> | B62: Elemental Resonance | C62: Armor Mod | D62: Bottoms | E62: General | F62: For each instance of Elemental DMG dealt from the previous magazine, the next magazine gains Elemental DMG +1% for 15s upon reloading, up to +24%. | G62: ouvrir | H62: ouvrir
A63: Elemental Resonance <Precision> | B63: Elemental Resonance | C63: Armor Mod | D63: Bottoms | E63: Precision | F63: For each instance of Elemental DMG dealt from the previous magazine, the next magazine gains Elemental DMG +1% for 15s upon reloading, up to +24%. | G63: ouvrir | H63: ouvrir
A64: Elemental Resonance <Resonance> | B64: Elemental Resonance | C64: Armor Mod | D64: Bottoms | E64: Resonance | F64: For each instance of Elemental DMG dealt from the previous magazine, the next magazine gains Elemental DMG +1% for 15s upon reloading, up to +24%. | G64: ouvrir | H64: ouvrir
A65: Elemental Resonance <Resonance Deviant Energy> | B65: Elemental Resonance | C65: Armor Mod | D65: Bottoms | E65: Resonance Deviant Energy | F65: For each instance of Elemental DMG dealt from the previous magazine, the next magazine gains Elemental DMG +1% for 15s upon reloading, up to +24%. | G65: ouvrir | H65: ouvrir
A66: Elemental Resonance <Survival> | B66: Elemental Resonance | C66: Armor Mod | D66: Bottoms | E66: Survival | F66: For each instance of Elemental DMG dealt from the previous magazine, the next magazine gains Elemental DMG +1% for 15s upon reloading, up to +24%. | G66: ouvrir | H66: ouvrir
A67: Elemental Resonance <Violent> | B67: Elemental Resonance | C67: Armor Mod | D67: Bottoms | E67: Violent | F67: For each instance of Elemental DMG dealt from the previous magazine, the next magazine gains Elemental DMG +1% for 15s upon reloading, up to +24%. | G67: ouvrir | H67: ouvrir
A68: Melee Momentum <Aero> | B68: Melee Momentum | C68: Armor Mod | D68: Bottoms | E68: Aero | F68: Killing with melee attacks restores 30% of Max Stamina and grants +20% Melee DMG for 8 seconds. | G68: ouvrir
A69: Melee Momentum <Aero Deviant Energy> | B69: Melee Momentum | C69: Armor Mod | D69: Bottoms | E69: Aero Deviant Energy | F69: Killing with melee attacks restores 30% of Max Stamina and grants +20% Melee DMG for 8 seconds. | G69: ouvrir
A70: Melee Momentum <Downstar> | B70: Melee Momentum | C70: Armor Mod | D70: Bottoms | E70: Downstar | F70: Killing with melee attacks restores 30% of Max Stamina and grants +20% Melee DMG for 8 seconds. | G70: ouvrir | H70: ouvrir
A71: Melee Momentum <Downstar Deviant Energy> | B71: Melee Momentum | C71: Armor Mod | D71: Bottoms | E71: Downstar Deviant Energy | F71: Killing with melee attacks restores 30% of Max Stamina and grants +20% Melee DMG for 8 seconds. | G71: ouvrir | H71: ouvrir
A72: Melee Momentum <Melee Default> | B72: Melee Momentum | C72: Armor Mod | D72: Bottoms | E72: Melee Default | F72: Killing with melee attacks restores 30% of Max Stamina and grants +20% Melee DMG for 8 seconds. | G72: ouvrir | H72: ouvrir
A73: Melee Momentum <Resonance> | B73: Melee Momentum | C73: Armor Mod | D73: Bottoms | E73: Resonance | F73: Killing with melee attacks restores 30% of Max Stamina and grants +20% Melee DMG for 8 seconds. | G73: ouvrir | H73: ouvrir
A74: Melee Momentum <Resonance Deviant Energy> | B74: Melee Momentum | C74: Armor Mod | D74: Bottoms | E74: Resonance Deviant Energy | F74: Killing with melee attacks restores 30% of Max Stamina and grants +20% Melee DMG for 8 seconds. | G74: ouvrir | H74: ouvrir
A75: Melee Momentum <Survival> | B75: Melee Momentum | C75: Armor Mod | D75: Bottoms | E75: Survival | F75: Killing with melee attacks restores 30% of Max Stamina and grants +20% Melee DMG for 8 seconds. | G75: ouvrir | H75: ouvrir
A76: Precise Charge <General> | B76: Precise Charge | C76: Armor Mod | D76: Bottoms | E76: General | F76: For every 10% Weakspot hit rate of the previous magazine, Elemental DMG +4%, up to 24%, lasting for 10s. Reloading resets the calculation. | G76: ouvrir | H76: ouvrir
A77: Precision Charge <Aero> | B77: Precision Charge | C77: Armor Mod | D77: Bottoms | E77: Aero | F77: For every 10% Weakspot hit rate of the previous magazine, Elemental DMG +4%, up to 24%, lasting for 10s. Reloading resets the calculation. | G77: ouvrir
A78: Precision Charge <Deviant Energy> | B78: Precision Charge | C78: Armor Mod | D78: Bottoms | E78: Deviant Energy | F78: For every 10% Weakspot hit rate of the previous magazine, Elemental DMG +4%, up to 24%, lasting for 10s. Reloading resets the calculation. | G78: ouvrir | H78: ouvrir
A79: Precision Charge <Downstar> | B79: Precision Charge | C79: Armor Mod | D79: Bottoms | E79: Downstar | F79: For every 10% Weakspot hit rate of the previous magazine, Elemental DMG +4%, up to 24%, lasting for 10s. Reloading resets the calculation. | G79: ouvrir | H79: ouvrir
A80: Precision Charge <Downstar Deviant Energy> | B80: Precision Charge | C80: Armor Mod | D80: Bottoms | E80: Downstar Deviant Energy | F80: For every 10% Weakspot hit rate of the previous magazine, Elemental DMG +4%, up to 24%, lasting for 10s. Reloading resets the calculation. | G80: ouvrir | H80: ouvrir
A81: Precision Charge <Precision> | B81: Precision Charge | C81: Armor Mod | D81: Bottoms | E81: Precision | F81: For every 10% Weakspot hit rate of the previous magazine, Elemental DMG +4%, up to 24%, lasting for 10s. Reloading resets the calculation. | G81: ouvrir | H81: ouvrir
A82: Precision Charge <Resonance> | B82: Precision Charge | C82: Armor Mod | D82: Bottoms | E82: Resonance | F82: For every 10% Weakspot hit rate of the previous magazine, Elemental DMG +4%, up to 24%, lasting for 10s. Reloading resets the calculation. | G82: ouvrir | H82: ouvrir
A83: Precision Charge <Resonance Deviant Energy> | B83: Precision Charge | C83: Armor Mod | D83: Bottoms | E83: Resonance Deviant Energy | F83: For every 10% Weakspot hit rate of the previous magazine, Elemental DMG +4%, up to 24%, lasting for 10s. Reloading resets the calculation. | G83: ouvrir | H83: ouvrir
A84: Precision Charge <Survival> | B84: Precision Charge | C84: Armor Mod | D84: Bottoms | E84: Survival | F84: For every 10% Weakspot hit rate of the previous magazine, Elemental DMG +4%, up to 24%, lasting for 10s. Reloading resets the calculation. | G84: ouvrir | H84: ouvrir
A85: Precision Charge <Violent> | B85: Precision Charge | C85: Armor Mod | D85: Bottoms | E85: Violent | F85: For every 10% Weakspot hit rate of the previous magazine, Elemental DMG +4%, up to 24%, lasting for 10s. Reloading resets the calculation. | G85: ouvrir | H85: ouvrir
A86: Reload Rampage <Aero> | B86: Reload Rampage | C86: Armor Mod | D86: Bottoms | E86: Aero | F86: After killing two enemies, refill 2 bullets from inventory (no more than 50% of the Magazine Capacity) grants Weapon DMG and Status DMG +10% until next reload. | G86: ouvrir
A87: Reload Rampage <Aero Deviant Energy> | B87: Reload Rampage | C87: Armor Mod | D87: Bottoms | E87: Aero Deviant Energy | F87: After killing two enemies, refill 2 bullets from inventory (no more than 50% of the Magazine Capacity) grants Weapon DMG and Status DMG +10% until next reload. | G87: ouvrir
A88: Reload Rampage <Deviant Energy> | B88: Reload Rampage | C88: Armor Mod | D88: Bottoms | E88: Deviant Energy | F88: After killing two enemies, refill 2 bullets from inventory (no more than 50% of the Magazine Capacity) grants Weapon DMG and Status DMG +10% until next reload. | G88: ouvrir | H88: ouvrir
A89: Reload Rampage <Downstar> | B89: Reload Rampage | C89: Armor Mod | D89: Bottoms | E89: Downstar | F89: After killing two enemies, refill 2 bullets from inventory (no more than 50% of the Magazine Capacity) grants Weapon DMG and Status DMG +10% until next reload. | G89: ouvrir | H89: ouvrir
A90: Reload Rampage <Downstar Deviant Energy> | B90: Reload Rampage | C90: Armor Mod | D90: Bottoms | E90: Downstar Deviant Energy | F90: After killing two enemies, refill 2 bullets from inventory (no more than 50% of the Magazine Capacity) grants Weapon DMG and Status DMG +10% until next reload. | G90: ouvrir | H90: ouvrir
A91: Reload Rampage <General> | B91: Reload Rampage | C91: Armor Mod | D91: Bottoms | E91: General | F91: After killing two enemies, refill 2 bullets from inventory (no more than 50% of the Magazine Capacity) grants Weapon DMG and Status DMG +10% until next reload. | G91: ouvrir | H91: ouvrir
A92: Reload Rampage <Precision> | B92: Reload Rampage | C92: Armor Mod | D92: Bottoms | E92: Precision | F92: After killing two enemies, refill 2 bullets from inventory (no more than 50% of the Magazine Capacity) grants Weapon DMG and Status DMG +10% until next reload. | G92: ouvrir | H92: ouvrir
A93: Reload Rampage <Resonance> | B93: Reload Rampage | C93: Armor Mod | D93: Bottoms | E93: Resonance | F93: After killing two enemies, refill 2 bullets from inventory (no more than 50% of the Magazine Capacity) grants Weapon DMG and Status DMG +10% until next reload. | G93: ouvrir | H93: ouvrir
A94: Reload Rampage <Resonance Deviant Energy> | B94: Reload Rampage | C94: Armor Mod | D94: Bottoms | E94: Resonance Deviant Energy | F94: After killing two enemies, refill 2 bullets from inventory (no more than 50% of the Magazine Capacity) grants Weapon DMG and Status DMG +10% until next reload. | G94: ouvrir | H94: ouvrir
A95: Reload Rampage <Survival> | B95: Reload Rampage | C95: Armor Mod | D95: Bottoms | E95: Survival | F95: After killing two enemies, refill 2 bullets from inventory (no more than 50% of the Magazine Capacity) grants Weapon DMG and Status DMG +10% until next reload. | G95: ouvrir | H95: ouvrir
A96: Reload Rampage <Violent> | B96: Reload Rampage | C96: Armor Mod | D96: Bottoms | E96: Violent | F96: After killing two enemies, refill 2 bullets from inventory (no more than 50% of the Magazine Capacity) grants Weapon DMG and Status DMG +10% until next reload. | G96: ouvrir | H96: ouvrir
A97: Status Amplification <Deviant Energy> | B97: Status Amplification | C97: Armor Mod | D97: Bottoms | E97: Deviant Energy | F97: When the magazine is empty, Status DMG +10% for 12s. Effect can stack up to 3 times. | G97: ouvrir | H97: ouvrir
A98: Status Amplification <Downstar> | B98: Status Amplification | C98: Armor Mod | D98: Bottoms | E98: Downstar | F98: When the magazine is empty, Status DMG +10% for 12s. Effect can stack up to 3 times. | G98: ouvrir | H98: ouvrir
A99: Status Amplification <Downstar Deviant Energy> | B99: Status Amplification | C99: Armor Mod | D99: Bottoms | E99: Downstar Deviant Energy | F99: When the magazine is empty, Status DMG +10% for 12s. Effect can stack up to 3 times. | G99: ouvrir | H99: ouvrir
... A105: Status Amplification <Violent> | B105: Status Amplification | C105: Armor Mod | D105: Bottoms | E105: Violent | F105: When the magazine is empty, Status DMG +10% for 12s. Effect can stack up to 3 times. | G105: ouvrir | H105: ouvrir
...

Sheet Deviations
A1: Name | B1: Type | C1: Rarity | D1: Effect | E1: Where to get | F1: Page | G1: Image
A2: Behemoth | B2: Combat | C2: Rare | D2: A loyal companion for Metas. | F2: ouvrir | G2: ouvrir
A3: Brave George | B3: Combat | C3: Epic | D3: A loyal companion for Metas. | F3: ouvrir | G3: ouvrir
A4: Butterfly's Emissary | B4: Combat | C4: Common | D4: Designated Target: designate a target to attack. Auto Attack: attacks enemies; marks the enemy's Weakspot on hit, making it take +25%/30%/35% extra Weakspot DMG for 5s. | E4: Tutoriel Eve of Evolution, GAIA Research Center Ruins, Silo Alpha | F4: ouvrir | G4: ouvrir
A5: By-The-Wind (PVE) | B5: Combat | C5: Legendary | D5: Gravity Lift (Takes effect after player takes the throw, creating a floating area on the ground.). Combat Assist (Generates a floating zone beneath the player, allowing them to freely float in the air at a fixed height. Player movement speed +20%, jump speed +2, and become immune to fall DMG and stagger.). | E5: Can be obtained by participating in a prime war and opening the reward crate. | F5: ouvrir
A6: By-the-Wind | B6: Combat | C6: Rare | D6: Gravity Lift: creates a floating area on the ground. Combat Assist: floating zone under the player (fixed height), Movement Speed +20%, jump speed +2, immune to fall DMG and stagger. | E6: Prime War | F6: ouvrir | G6: ouvrir
A7: Chaos - Mini Wonder | B7: Combat | C7: Epic | D7: Designated Target: buffs an ally. Bullet Absorption: absorbs bullets within a radius. | E7: Tâche « Other World Traveler » (Lowe) | F7: ouvrir | G7: ouvrir
A8: Chaos Mr. Wish | B8: Combat | C8: Epic | D8: Rapid Fire: bursts at enemies near the crosshair, marking them with The Bull's Eye. Auto Attack. | E8: Silo SIGMA | F8: ouvrir | G8: ouvrir
A9: Chaos Snowsprite | B9: Combat | C9: Epic | D9: Auto Attack: generates Ice Crystals near the target every 3s. Crystals shatter when shot, dealing 37.5% to 87.5% Frost DMG to nearby targets and making them take +18% to +42% Frost DMG. | E9: Tâche « Deviation: Snowsprite » (Lowe) | F9: ouvrir | G9: ouvrir
A10: Chaos Zeno-Purifier | B10: Combat | C10: Epic | D10: Designated Target + Auto Attack: lets the player teleport to the target with melee attacks. | E10: Objectif saisonnier « 200 ennemis en mêlée » ou coffres | F10: ouvrir | G10: ouvrir
A11: Chaosaurus | B11: Combat | C11: Epic | D11: Abilities: Straight-line Burn, Telekinetic Effects. Can participate in combat to breathe fire. | F11: ouvrir | G11: ouvrir
A12: Chuckles | B12: Combat | C12: Rare | D12: A loyal companion for Metas. | F12: ouvrir | G12: ouvrir
A13: Dr. Teddy | B13: Combat | C13: Rare | D13: Remote Healing: throw to heal 50% Max HP instantly and revive a downed target. Intime Healing: 8% Max HP heal per second, revives allies. | E13: Silo THETA | F13: ouvrir | G13: ouvrir
A14: Enchanting Void | B14: Combat | C14: Epic | D14: Midnight Maul: player transforms into a panther for 20s, auto-attacks and increases melee DMG taken by targets. Combat Assist: Movement Speed +10% with a melee weapon, recover 10% Max HP on melee hit. | E14: Silo THETA (énigme des statues) | F14: ouvrir | G14: ouvrir
A15: Enchanting Void (PVE) | B15: Combat | C15: Legendary | D15: Midnight Maul. Combat Assist. | E15: Silo Theta (PVE). | F15: ouvrir
A16: Festering Gel | B16: Combat | C16: Common | D16: Flawless Fortification: knocks back enemies and forms a shelter. Build Fortification: fixed shelter that blocks attacks; allies nearby recover 6% HP and 3% Sanity per second. | E16: Monolith of Greed (Ravenous Hunter), Gaia Cliff Monolith (Treant) | F16: ouvrir | G16: ouvrir
A17: Gazacchio | B17: Combat | C17: Legendary | D17: Works within the territory to guard it, capable of producing a special tactical item to despel shadows. | E17: Can Randomly be Obtained after Defeating Shadow Enemies. Gazocchio Quest ( Whalebone Settlement in Vena Fjord - Lowe). | F17: ouvrir
A18: Grumpy Bulb | B18: Combat | C18: Rare | D18: Garlicify: AoE Status DMG on hit and disrupts aggro for 10s. Autonomous Attack: cannot move, continuously attracts aggro of nearby enemies. | E18: Graine d'oignon mature à la base | F18: ouvrir | G18: ouvrir
A19: Invincible Sun | B19: Combat | C19: Rare | D19: Autonomous Attack: periodically releases blazing energy rays that hit all nearby enemies, inflicting continuous Burn DMG. | E19: Silo Delta | F19: ouvrir | G19: ouvrir
A20: Lonewolf's Whisper | B20: Combat | C20: Rare | D20: Designated Target + Auto Attack: attacks enemies and attracts their aggro; spawns a clone when a target dies. Increases Weapon DMG received by the attacked target by 21.6% (Lunar version: +5% Weapon DMG, +10% at low Sanity). | E20: Monolith of Thirst (Shadow Hound) | F20: ouvrir | G20: ouvrir
A21: Mini Feaster | B21: Combat | C21: Epic | D21: Touch of the Abyss: follows the player, summons tentacles near enemies to smash. When a target triggers Bounce, tentacles are guaranteed next to it and enhance the player's Weapon DMG. | E21: Tâche « Lord of the Quest » (Lowe) ou événements Mist Zone | F21: ouvrir | G21: ouvrir
A22: Mini Wonder | B22: Combat | C22: Epic | D22: Designated Target: buffs an ally. Bullet Absorption: absorbs bullets within a radius. | E22: Tâche « Other World Traveler » (Lowe) | F22: ouvrir | G22: ouvrir
A23: Mr. Wish | B23: Combat | C23: Epic | D23: Rapid Fire: bursts at enemies near the crosshair, marking them with The Bull's Eye. Auto Attack. | E23: Silo SIGMA | F23: ouvrir | G23: ouvrir
A24: Polar Jelly | B24: Combat | C24: Rare | D24: Frostlash: knocks back enemies and forms a fortification. Auto Attack: continuously deals Frost Status DMG to surrounding enemies and pulls them toward it; increases Frost DMG received by 36%. Frost Vortexes formed inside its radius create additional Ice Spikes. | E24: Événements Cargo Scramble | F24: ouvrir | G24: ouvrir
A25: Pyro Dino | B25: Combat | C25: Epic | D25: Designated Target + Autonomous Attack: attacks enemies, increases Blaze DMG received by 24.5%. Attacking a target affected by Burn causes an Explosion. | E25: Silo PHI | F25: ouvrir | G25: ouvrir
A26: Radiant One | B26: Combat | C26: Epic | D26: Combat Assist: floating zone under the player, Movement Speed +20%, jump speed +2, immune to fall DMG and stagger. | E26: Phase 3 de The Last Stand (Prismverse's Clash) | F26: ouvrir | G26: ouvrir
A27: Shattered Maiden | B27: Combat | C27: Common | D27: Designated Target + Auto Attack: inflicts Slowdown and Chained to non-boss enemies in front, and increases their Explosion DMG received by 40%. | E27: Tâche « Farmside Fright » (Lowe) ou Silo THETA | F27: ouvrir | G27: ouvrir
A28: Snapshot | B28: Combat | C28: Legendary | D28: Can participate in combat to constantly photograph nearby enemies, increasing the Weapon DMG they receive. | E28: Clear the Tundra Monolith in Onyx Tundra. | F28: ouvrir
A29: Snowsprite | B29: Combat | C29: Epic | D29: Auto Attack: generates Ice Crystals near the target every 3s. Crystals shatter when shot, dealing 37.5% to 87.5% Frost DMG to nearby targets and making them take +18% to +42% Frost DMG. | E29: Tâche « Deviation: Snowsprite » (Lowe) | F29: ouvrir | G29: ouvrir
A30: Soul Summoner | B30: Combat | C30: Rare | D30: Abilities: Vulnerability Mark, Fire Boost. Can participate in combat to weaken enemies with cursed... | F30: ouvrir | G30: ouvrir
A31: Strange Goose: Mr. Wish | B31: Combat | C31: Legendary | F31: ouvrir
A32: Voodoo Doll | B32: Combat | C32: Rare | D32: Designated Target: shares part of the DMG taken (ally) or makes an enemy share DMG taken by the player. Doppelganger: shares half of the DMG received by the player. | E32: Evergreen Vineyard (Chalk Peak), Fort Erie (Red Sands), hôpitaux | F32: ouvrir | G32: ouvrir
A33: Watcher | B33: Combat | C33: Rare | D33: A loyal companion for Metas. | F33: ouvrir | G33: ouvrir
A34: Whalepup | B34: Combat | C34: Rare | D34: Abilities: Transformation Effect, Waterflow Restraint. Can participate in combat, transforming the... | F34: ouvrir | G34: ouvrir
A35: ZapCam | B35: Combat | C35: Rare | D35: Manual Photograph: locks onto an enemy before dealing damage. Auto Photograph: teleports to targets and takes photos dealing Status DMG; the enemy receives +21.6% Weapon DMG. | E35: Tundra Monolith (Secret Servitor) | F35: ouvrir | G35: ouvrir
A36: Zapamander | B36: Combat | C36: Epic | D36: Abilities: Sprint Boost, Silence Effect. Can participate in combat to summon thunderclouds to strike... | F36: ouvrir | G36: ouvrir
A37: Zeno-Purifier | B37: Combat | C37: Epic | D37: Designated Target + Auto Attack: lets the player teleport to the target with melee attacks. | E37: Objectif saisonnier « 200 ennemis en mêlée » ou coffres | F37: ouvrir | G37: ouvrir
A38: Artisan's Touch | B38: Crafting | C38: Rare | D38: Formula: All-Purpose Hand: repairs the least durable gear you equip (crafted gear only). | E38: Élite Scorcher | F38: ouvrir | G38: ouvrir
A39: Atomic Lighter | B39: Crafting | C39: Rare | D39: Tactical Item: Uncontrollable Fusion Lighter: random instances of damage; extra loot on kills. | E39: Silo EX1 | F39: ouvrir | G39: ouvrir
A40: Atomic Snail | B40: Crafting | C40: Rare | D40: Whim: Fluid Type: sprint a short distance in the air. | E40: Stardust Advent III (Prime Wars) | F40: ouvrir | G40: ouvrir
A41: Chaos Dice | B41: Crafting | C41: Legendary | F41: ouvrir
A42: Disco Ball | B42: Crafting | C42: Common | D42: Whim: Utter Delight: extends the duration of other Whims. | E42: Événement « Hale's Moving House » / « Where Does Disco Go? » | F42: ouvrir | G42: ouvrir
A43: Dreamcatcher | B43: Crafting | C43: Common | D43: Whim: Web of Silk: spits a spider web to restrain enemies when in danger. | E43: Mirage Monolith (Arachsiam) | F43: ouvrir | G43: ouvrir
A44: Frog the Leaper | B44: Crafting | C44: Common | D44: Whim: Spring Legs: greatly enhances jump height (consumes stamina). | E44: Sommets de piles de voitures | F44: ouvrir | G44: ouvrir
A45: Gingerbread House | B45: Crafting | C45: Rare | D45: Tactical Item: Transformation Cookie: turns you into any object in the scene. | E45: Morphic Crates ou tâche « Morphic Decoy » (Lowe) | F45: ouvrir | G45: ouvrir
A46: Harveseed | B46: Crafting | C46: Rare | D46: Whim: Chloro-armor: when life is fading, new vitality is unleashed. | E46: Gaia Cliff Monolith (Treant) | F46: ouvrir | G46: ouvrir
A47: Ice Pot | B47: Crafting | C47: Common | D47: Sticky Ice Crystal: produces a magical adhesive ice block. | E47: Tâche « Deviation: Ice Pot » (Lowe) | F47: ouvrir | G47: ouvrir
A48: Masonic Pyramid | B48: Crafting | C48: Common | D48: Whim: Predator: the first hit after leaving combat and diving is a guaranteed Crit. | E48: Stronghold Conquests (Iron River) | F48: ouvrir | G48: ouvrir
A49: Orb Lightning | B49: Crafting | C49: Common | D49: Tactical Item: Lightning Bottle: boosts nearby Turrets. | E49: Rosetta Research Institutes, bases militaires | F49: ouvrir | G49: ouvrir
A50: Party Monkey | B50: Crafting | C50: Common | D50: Formula: Party Monkey: facility that draws monster aggro nearby. | E50: Événements Production Facility | F50: ouvrir | G50: ouvrir
A51: Pup Buddy | B51: Crafting | C51: Rare | D51: Whim: Featherweight: Max Load increased. | E51: Jonathan (Greywater Camp), Blackfell, Evergreen | F51: ouvrir | G51: ouvrir
A52: Snow Globe | B52: Crafting | C52: Common | D52: Formula: Snowball: Slowdown on hit, Frozen on multiple hits. | E52: Silo PSI | F52: ouvrir | G52: ouvrir
A53: Space Turner | B53: Crafting | C53: Rare | D53: Tactical Item: Space Twister: creates a Teleport Door and summons teammates. | E53: Mystical Crates | F53: ouvrir | G53: ouvrir
... A57: Berserkosaurus Rex | B57: Territory | C57: Epic | D57: Culinary Genius: increases cooking proficiency (scales with Deviant Energy). | E57: Phase 2 du Clash at Blackfell | F57: ouvrir | G57: ouvrir
A58: Blackback | B58: Territory | C58: Common | D58: Abilities: Furrever Friends. A loyal companion for Metas. | F58: ouvrir | G58: ouvrir
A59: Blackfell | B59: Territory | C59: Rare | D59: Abilities: Strange Medicine. Work in the Territory to improve Supplies Workbench efficiency. Crafted... | F59: ouvrir | G59: ouvrir
A60: Buzzy Bee | B60: Territory | C60: Common | D60: Deviated Gardening: increases crop mutation chance (scales with Deviant Energy). | E60: Sunbury Farm, Evergreen Vineyard, Brewery Estate | F60: ouvrir | G60: ouvrir
A61: Cattiva | B61: Territory | C61: Epic | D61: Abilities: Mine Ore. Works in the Territory to gather Ores or works at the Mining Platform. | F61: ouvrir | G61: ouvrir
A62: Chaotic Extradimensional Cat | B62: Territory | C62: Epic | D62: Velvet Cushion: sleeps with its owner so they're fully energetic the next day. | E62: Près des tours de téléportation des bastions de l'Union | F62: ouvrir | G62: ouvrir
A63: Chefosaurus Rex | B63: Territory | C63: Epic | D63: Culinary Genius: increases cooking proficiency (scales with Deviant Energy). | E63: Tâche « There's a Dragon There » (Lowe) ou Silo PHI | F63: ouvrir | G63: ouvrir
A64: Chillet | B64: Territory | C64: Rare | D64: Abilities: Velvet Cushion. Enjoys itself inside the Territory. Accompanies its owner to sleep to make sure... | F64: ouvrir | G64: ouvrir
A65: Director Fox | B65: Territory | C65: Rare | D65: Abilities: Taming Expert. Working in your territory helps tame, grow, and breed animals. | F65: ouvrir | G65: ouvrir
A66: Doberman | B66: Territory | C66: Common | D66: Abilities: Furrever Friends. A loyal companion for Metas. | F66: ouvrir | G66: ouvrir
A67: Doctor Raven | B67: Territory | C67: Legendary | F67: ouvrir
A68: Electric Eel | B68: Territory | C68: Common | D68: Electricity Fluctuations: increases the power limit of Generators. | E68: Pêche | F68: ouvrir | G68: ouvrir
A69: Extradimensional Cat | B69: Territory | C69: Epic | D69: Velvet Cushion: sleeps with its owner so they're fully energetic the next day. | E69: Près des tours de téléportation des bastions de l'Union | F69: ouvrir | G69: ouvrir
A70: Fetch-A-Lot Bunny | B70: Territory | C70: Common | D70: Collect from bushes: automatically gathers shrubs. | E70: Dracaena (Red Sands), Bald Cypress (Iron River) | F70: ouvrir | G70: ouvrir
A71: Flame Essence | B71: Territory | C71: Common | D71: Molten Heat: increases Furnace and Electric Furnace production efficiency. | E71: Hearst Industries (Broken Delta) ou Silo PSI | F71: ouvrir | G71: ouvrir
A72: Gazocchio | B72: Territory | C72: Epic | D72: Territory Guard: patrols and attacks intruders; conjures tiny Gazocchio that shine light to dispel shadows. | E72: Tâche « Part of the Deviant » (Lowe) | F72: ouvrir | G72: ouvrir
A73: Growshroom | B73: Territory | C73: Rare | D73: Thriving Growth: automatically plants seeds and accelerates crop growth. | E73: Récolte de champignons sauvages | F73: ouvrir | G73: ouvrir
A74: H37 | B74: Territory | C74: Rare | D74: Explorer: loots chests in different areas and brings back goodies. | E74: Tâche « Fragments of Memory » ou Silo ALPHA | F74: ouvrir | G74: ouvrir
A75: Hug-in-a-Bowl | B75: Territory | C75: Common | D75: Food: Homemade Noodles: restores Sanity to full. | E75: Cuisiner le plat Hug-in-a-Bowl | F75: ouvrir | G75: ouvrir
A76: Hydronaut Fish | B76: Territory | C76: Rare | D76: Rapid Purification: gathers seawater, occasional special catches; boosts Water Filter / Brewing Barrel efficiency. | E76: Tâche « Deviation: Hydronaut Fish » (Lowe) | F76: ouvrir | G76: ouvrir
A77: Labrador | B77: Territory | C77: Common | D77: Abilities: Furrever Friends. A loyal companion for Metas. | F77: ouvrir | G77: ouvrir
A78: Lethal Rabbit | B78: Territory | C78: Rare | D78: Hunter Instincts: explores and hunts, bringing back animal resources. | E78: Deadsville, Heart Island, Evergreen | F78: ouvrir | G78: ouvrir
A79: Logging Beaver | B79: Territory | C79: Rare | D79: Log Trees: goes out logging; uses a Logging Operation Platform if available. | E79: Meyer's Market, Iron River, Broken Delta | F79: ouvrir | G79: ouvrir
A80: Night Watch Lamp | B80: Territory | C80: Epic | D80: Abilities: Territory Guard. Unavailable in certain Arena battles. Used for display icons only. | F80: ouvrir | G80: ouvrir
A81: Nutcracker | B81: Territory | C81: Rare | D81: Mobile Turret: patrols the territory and attacks intruders. | E81: Forsaken Monolith (Forsaken Giant) | F81: ouvrir | G81: ouvrir
A82: Paper Doll | B82: Territory | C82: Common | D82: Safe Haven Barrier: walls, floors and the Stardust Resonant Filter auto-recover durability; chance of rewards when killing invading Deviants. | E82: Partout sur Nalcott | F82: ouvrir | G82: ouvrir
A83: Peach Weasel | B83: Territory | C83: Rare | D83: Abilities: Velvet Cushion. Enjoys itself inside the Territory. Accompanies its owner to sleep to make... | F83: ouvrir | G83: ouvrir
A84: Rain Man | B84: Territory | C84: Rare | D84: Hoping for a downpour: boosts crop vitality and provides irrigation water. | E84: Harborside (Broken Delta), Greywater (Iron River), Unmarked Settlement (Chalk Peak) | F84: ouvrir | G84: ouvrir
A85: Rebecca | B85: Territory | C85: Epic | D85: Energy Recover: Mitsuko plays piano and improves Deviant Energy recovery efficiency. | E85: Boss final du LEA Research Lab | F85: ouvrir | G85: ouvrir
A86: Tar Pudding | B86: Territory | C86: Rare | D86: Oil Gathering: gathers fuel around the territory; accelerates refinery conversion. | E86: Avalanche Monolith (Vena Fjord) | F86: ouvrir | G86: ouvrir
A87: The Digby Boy | B87: Territory | C87: Common | D87: Mine Ore: goes out mining; uses a Mining Operation Platform if available. | E87: Tâche « Deviation Expert » (Lowe) ou minage d'argent | F87: ouvrir | G87: ouvrir
A88: Wish Box | B88: Territory | C88: Rare | D88: Unfair Trade: transforms items placed inside into random new items. | E88: Morphic Crates ou Severin VII-S2401 | F88: ouvrir | G88: ouvrir

Sheet Overrides
A1: Name | B1: Category | C1: Effect | D1: Page | E1: Image
A2: Aerial Suppression | B2: Combat | C2: While airborne, DMG received from monsters is reduced by 30%. | D2: ouvrir | E2: ouvrir
A3: Agility | B3: Combat | C3: After rolling, Weapon DMG Reduction/n+15% and Status DMG Reduction +15% for 4s. | D3: ouvrir | E3: ouvrir
A4: Ammo Cascade | B4: Combat | C4: After performing a successful backstab/execution/impact, Melee DMG +0.3% and Movement Speed +0.1% for 10s. | D4: ouvrir | E4: ouvrir
A5: Anti-Coherence | B5: Combat | C5: When using Pistols, Light Machine Guns or Melee Weapons , DMG +15%, with an additional 100% DMG against Super Anomaly - Coherence. | D5: ouvrir | E5: ouvrir
A6: Anti-Phase | B6: Combat | C6: When using Sniper Rifles, SMGs or Crossbows DMG +15%, with an additional 100% DMG against Super Anomaly - Phase. | D6: ouvrir | E6: ouvrir
A7: Anti-Regen | B7: Combat | C7: When using pistols, light machine guns, or melee weapons, DMG +15%, with an additional 100% DMG against Super Anomaly - Regen. | D7: ouvrir | E7: ouvrir
A8: Anti-Void | B8: Combat | C8: When using Rifles, Shotguns or Heavy Weapons DMG +15%, with an additional 100% DMG against Super Anomaly - Void. | D8: ouvrir | E8: ouvrir
A9: Automatic Weapon Enhancement | B9: Combat | C9: DMG +20% when holding SMGs, Rifles or LMGs. Reload 10% of the magazine capacity from reserve upon defeating an enemy. | D9: ouvrir | E9: ouvrir
A10: Blazing Detonation | B10: Combat | C10: When inflicting Burn or a unit that already has Burn, immediately deal one instance of Burn DMG (Cooldown: 3s) and gain Burn DMG +25% for 10s. | D10: ouvrir | E10: ouvrir
A11: Bounce Rampage | B11: Combat | C11: After triggering a bounce, Bounce DMG +5% for 15 seconds. Up to 5 stacks. | D11: ouvrir | E11: ouvrir
A12: Bounce Rampage | B12: Combat | C12: Upon landing a Bounce shot, Bounce DMG +10% for 5s. Up to 15 stacks. | D12: ouvrir | E12: ouvrir
... A171: Sniper Rifle Weakspot DMG Boost | B171: Specialist | C171: When in Scope mode, Sniper Rifle Weakspot DMG +30%, Accuracy +20 | D171: ouvrir | E171: ouvrir

Sheet Calibrations
A1: Name | B1: Short name | C1: Rarity | D1: Page | E1: Image
A2: Calibration Blueprint - 12-Gauge | B2: 12-Gauge | C2: Rare | D2: ouvrir | E2: ouvrir
A3: Calibration Blueprint - 16-Gauge | B3: 16-Gauge | C3: Rare | D3: ouvrir | E3: ouvrir
A4: Calibration Blueprint - 20-Gauge | B4: 20-Gauge | C4: Rare | D4: ouvrir | E4: ouvrir
A5: Calibration Blueprint - Assault Machine Gun | B5: Assault Machine Gun | C5: Rare | D5: ouvrir | E5: ouvrir
A6: Calibration Blueprint - Assault SMG | B6: Assault SMG | C6: Rare | D6: ouvrir | E6: ouvrir
A7: Calibration Blueprint - Boost Pistol | B7: Boost Pistol | C7: Epic | D7: ouvrir | E7: ouvrir
A8: Calibration Blueprint - Boost Shotgun | B8: Boost Shotgun | C8: Epic | D8: ouvrir | E8: ouvrir
A9: Calibration Blueprint - Capacity Expander | B9: Capacity Expander | C9: Rare | D9: ouvrir | E9: ouvrir
A10: Calibration Blueprint - Energy Rifle | B10: Energy Rifle | C10: Epic | D10: ouvrir | E10: ouvrir
A11: Calibration Blueprint - Energy SMG | B11: Energy SMG | C11: Epic | D11: ouvrir | E11: ouvrir
A12: Calibration Blueprint - Frugal Pistol | B12: Frugal Pistol | C12: Epic | D12: ouvrir | E12: ouvrir
... A38: Calibration Blueprint - Vanguard SMG | B38: Vanguard SMG | C38: Epic | D38: ouvrir | E38: ouvrir

Sheet Food
A1: Name | B1: Category | C1: Rarity | D1: Weight (kg) | E1: Effect | F1: Page | G1: Image
A2: All-Weather Stew | B2: Food | C2: Legendary | D2: 0.15 | E2: +100 Energy, +100 Hydration. | F2: ouvrir | G2: ouvrir
A3: Anti-gravity Milkshake | B3: Food | C3: Legendary | D3: 0.05 | E3: +100 Energy, +100 Hydration. | F3: ouvrir | G3: ouvrir
A4: Aromatic Fruit and Roasted Meat | B4: Creative Cuisine | C4: Epic | D4: 0.1 | E4: Once Human Aromatic Fruit and Roasted Meat — Epic Creative Cuisine. +80 Energy. | F4: ouvrir | G4: ouvrir
A5: Aromatic Land & Sea Vegetable Platter | B5: Creative Cuisine | C5: Epic | D5: 0.1 | E5: Once Human Aromatic Land & Sea Vegetable Platter — Epic Creative Cuisine. +80 Energy. | F5: ouvrir | G5: ouvrir
A6: Assorted Canned Fruit | B6: Food | C6: Epic | D6: 0.15 | E6: +80 Energy, +40 Hydration. | F6: ouvrir | G6: ouvrir
A7: Bacon Burger | B7: Food | C7: Legendary | D7: 0.2 | E7: +100 Energy. | F7: ouvrir | G7: ouvrir
A8: Bone-in Deviated Sausage | B8: Food | C8: Epic | D8: 0.15 | E8: +100 Energy. | F8: ouvrir | G8: ouvrir
A9: Borscht Deluxe | B9: Food | C9: Epic | D9: 0.1 | E9: +100 Energy, +50 Hydration. | F9: ouvrir | G9: ouvrir
A10: Butter Matsutake Mushrooms | B10: Food | C10: Legendary | D10: 0.15 | E10: +100 Energy. | F10: ouvrir | G10: ouvrir
A11: Canned Lunch Meat | B11: Food | C11: Epic | D11: 0.15 | E11: +80 Energy. | F11: ouvrir | G11: ouvrir
A12: Canned Minty Meat | B12: Food | C12: Legendary | D12: 0.15 | E12: +100 Energy. | F12: ouvrir | G12: ouvrir
A13: Canned Seafood in Oil | B13: Food | C13: Legendary | D13: 0.15 | E13: +100 Energy. | F13: ouvrir | G13: ouvrir
... A155: Yuanbao Dumplings | B155: Food | C155: Legendary | D155: 0.15 | E155: +100 Energy. | F155: ouvrir | G155: ouvrir

Sheet Skins
A1: Name | B1: Rarity | C1: Hide set (×4) | D1: Helmet | E1: Mask | F1: Top | G1: Gloves | H1: Bottoms | I1: Shoes | J1: Page | K1: Image | L1: Status
A2: Anglerfish Skin | B2: Epic | D2: Pollution Resist +10, plus an extra +20 while exploring in water. | E2: When fighting in water, gain +2% Crit DMG for every 20% Sanity possessed. | F2: Cold Resist and Frost Resist +15. | G2: Fish Fillet yield +15%. | H2: Cold Resist and Frost Resist +15. | I2: Max Stamina +10; doubles while exploring in water. | J2: ouvrir
A3: Bay Crocodile Skin | B3: Epic | C3: Driftwood in the Water | D3: DMG Reduction +5% when Hydration is at 100. | E3: Crit DMG +10% when fighting in water. | F3: Heat/Burn Resist +15, plus an additional +10 while Soaked. | G3: Logging and Mining yield +25% for the final strike only. | H3: Heat/Burn Resist +15, plus an additional +10 while Soaked. | I3: Roll Stamina consumption -20%, plus an additional -40% while Soaked. | J3: ouvrir
A4: Beach Crocodile Skin | B4: Legendary | C4: Driftwood in the Water | D4: DMG Reduction +4%, but Hydration drains 30% faster while in combat. | E4: Melee Crit Rate +7%. | F4: Heat/Burn Resist +15, Dampened duration +50%, and DMG Reduction +5% while Dampened. | G4: Logging and Mining yield +25% for the final strike only. | H4: Heat/Burn Resist +15, Dampened duration +50%, and DMG Reduction +5% while Dampened. | I4: Roll Speed +20% when Stamina exceeds 80. | J4: ouvrir | K4: ouvrir
A5: Bear Skin | B5: Rare | C5: Power of Bears | D5: DMG Reduction +3% when Energy is at 100. | E5: Frost Elemental DMG +5%. | F5: Cold/Frost Resist +10; recover 3% HP on kill at 10°C or below. | G5: Deer Meat, Beef, Goat Meat, and Pork yield +10%. | H5: Cold/Frost Resist +10; recover 3% HP on kill at 10°C or below. | I5: Movement Speed +8% at 10°C or below. | J5: ouvrir | K5: ouvrir
A6: Bubble Fish Skin | B6: Epic | D6: Recover 10% oxygen every 5s while diving. | E6: Crit Rate +5% when fighting in water. | F6: Heat, Burn, Cold, and Frost Resist +10. | G6: Fish Fillet yield +15%. | H6: Heat, Burn, Cold, and Frost Resist +10. | I6: Max Vital Capacity +30%. | J6: ouvrir
A7: Cave Bear Skin | B7: Legendary | C7: Power of Bears | D7: Upon taking damage, expend 10 Energy to recover 10% HP. Cooldown 30s. | E7: Elemental DMG +7% while crouched. | F7: Cold/Frost Resist +10; Energy depletion rate -25% while in Cold status. | G7: Deer Meat, Beef, Goat Meat, and Pork yield +15%. | H7: Cold/Frost Resist +10; Energy depletion rate -25% while in Cold status. | I7: Movement Speed +20% while in any territory. | J7: ouvrir | K7: ouvrir
A8: Coastal Bay Crocodile Skin | B8: Legendary | C8: Driftwood in the Water | D8: DMG Reduction +10% while invisible. | E8: Crit DMG +10% while invisible. | F8: Heat/Burn Resist +15 and Status DMG Reduction +5%. | G8: Logging and Mining yield +25% for the final strike only. | H8: Heat/Burn Resist +15 and Status DMG Reduction +5%. | I8: Roll Speed +12%. | J8: ouvrir | K8: ouvrir
A9: Cowhide | B9: Rare | C9: Impacter | D9: Crit DMG Reduction +7%. | E9: Weapon DMG +5% when Stamina is at least 100. | F9: Max Load +20. | G9: Grain yield +10%. | H9: Max Load +20. | I9: Max Stamina +10. | J9: ouvrir | K9: ouvrir
A10: Crocodile Hide | B10: Rare | C10: Driftwood in the Water | D10: DMG Reduction +3% when Hydration is at 100. | E10: Melee DMG +10%. | F10: Heat/Burn Resist +10 and Dampened duration +50%. | G10: Logging and Mining yield +20% for the final strike only. | H10: Heat/Burn Resist +10 and Dampened duration +50%. | I10: Roll Speed +8%. | J10: ouvrir | K10: ouvrir
A11: Deer Hide | B11: Uncommon | C11: Stag | D11: DMG Reduction +3% while sprinting. | E11: Impact DMG +12%. | F11: Cold Resist and Frost Resist +5. | G11: Logging and Mining Speed +10%. | H11: Cold Resist and Frost Resist +5. | I11: Sprint Speed +6%. | J11: ouvrir | K11: ouvrir
A12: Desert Fox Skin | B12: Epic | C12: Fox Shadow | D12: When not in combat, recover 0.5% HP/s, but Hydration drains 50% faster. | E12: Crit DMG +10% when not in combat. | F12: Enemies take 15% longer to notice you. | G12: Egg yield +15%. | H12: Enemies take 15% longer to notice you. | I12: Movement Speed +30% while crouched. | J12: ouvrir | K12: ouvrir
A13: Deviated Shark Hide | B13: Epic | D13: DMG Reduction +6% when fighting in water. | E13: Weapon DMG +4.5%, doubled while fighting in water. | F13: Max Stamina +30 and Cold/Frost Resist +10. | G13: Fish Fillet yield +15%. | H13: Max Stamina +30 and Cold/Frost Resist +10. | I13: Swim Speed +25%. | J13: ouvrir
A14: Dreamfused Cowhide | B14: Legendary | C14: Impacter | D14: Crit DMG Reduction +7%; doubles in the Dream Zone. | E14: Weapon DMG +5% when Stamina is 100 or higher; doubles in the Dream Zone. | F14: Max Load +20; doubles in the Dream Zone. | G14: 20% chance to obtain an additional Nightmare Light Source under Evernight. | H14: Max Load +20; doubles in the Dream Zone. | I14: Max Stamina +10; doubles in the Dream Zone. | J14: ouvrir | K14: ouvrir
A15: Dreamfused Deer Hide | B15: Legendary | C15: Stag | D15: While sprinting, DMG Reduction +3%; doubles in the Dream Zone. | E15: Impact DMG +12%; doubles in the Dream Zone. | F15: Cold/Frost Resist +5; doubles in the Dream Zone. | G15: 20% chance to obtain extra items when gathering Sea Water or Dirty Water. | H15: Cold/Frost Resist +5; doubles in the Dream Zone. | I15: Climb Speed +6%; doubles in the Dream Zone. | J15: ouvrir | K15: ouvrir
A16: Dreamfused Rabbit Fur | B16: Legendary | C16: Soaring Leap | D16: While airborne, DMG Reduction +5%; doubles in the Dream Zone. | E16: Elemental DMG +4%; doubles in the Dream Zone. | F16: Cold/Frost Resist +5; doubles in the Dream Zone. | G16: Gathering Wakeful Clocks yields 20% more Wakeful Sand. | H16: Cold/Frost Resist +5; doubles in the Dream Zone. | I16: Jump Height +8%; doubles in the Dream Zone. | J16: ouvrir | K16: ouvrir
A17: Dreamfused Wolf Skin | B17: Legendary | C17: Wolf Pack | D17: Weakspot DMG Reduction +5%; doubles in the Dream Zone. | E17: Weakspot DMG +3%; doubles in the Dream Zone. | F17: Max Stamina +15; doubles in the Dream Zone. | G17: 20% chance to gain an additional Dreamfused fur/hide when hunting in the Dream Zone. | H17: Max Stamina +15; doubles in the Dream Zone. | I17: Movement Speed +4%; doubles in the Dream Zone. | J17: ouvrir | K17: ouvrir
A18: Dreamfused Wool | B18: Legendary | C18: Herd Effect | D18: Non-Weakspot DMG Reduction +5%; doubles in the Dream Zone. | E18: Status DMG +4%; doubles in the Dream Zone. | F18: Cold/Frost Resist +10; doubles in the Dream Zone. | G18: Stardust Ore gathered increases by 20% in the Dream Zone. | H18: Cold/Frost Resist +10; doubles in the Dream Zone. | I18: Climb Speed +10%; doubles in the Dream Zone. | J18: ouvrir | K18: ouvrir
A19: Dreamy Rabbit Fur | B19: Legendary | C19: Soaring Leap | D19: DMG Reduction +8% while vaulting. | E19: Elemental DMG +6%. | F19: Cold/Frost Resist +10 and Heat/Burn Resist +5. | G19: Herb Seed yield +15%. | H19: Cold/Frost Resist +10 and Heat/Burn Resist +5. | I19: Jump Height +10%. | J19: ouvrir | K19: ouvrir
A20: Floating Ice Bear Skin | B20: Legendary | C20: Power of Bears | D20: DMG Reduction +4% when Energy exceeds 60. | E20: Frost Elemental DMG +8% when Energy is at 100. | F20: Cold/Frost Resist +15; recover 5% HP on kill at 10°C or below. | G20: Deer Meat, Beef, Goat Meat, and Pork yield +15%. | H20: Cold/Frost Resist +15; recover 5% HP on kill at 10°C or below. | I20: Movement Speed +15% at -10°C or below. | J20: ouvrir | K20: ouvrir
A21: Forest Deer Hide | B21: Epic | C21: Stag | D21: DMG Reduction +5% while scoped. | E21: Impact Crit Rate +20%. | F21: Cold/Frost Resist +5; when noticed by an enemy, Sprint Speed -10%. | G21: Logging and Mining Speed +12%. | H21: Cold/Frost Resist +5; when noticed by an enemy, Sprint Speed -10%. | I21: Sprint Speed +12%, but Sprinting Stamina cost +30%. | J21: ouvrir | K21: ouvrir
A22: Fox Skin | B22: Uncommon | C22: Fox Shadow | D22: DMG Reduction +10% when not in combat. | E22: Crit DMG +6% when not in combat. | F22: Enemies take 10% longer to notice you. | G22: Egg yield +10%. | H22: Enemies take 10% longer to notice you. | I22: Movement Speed +16% while crouched. | J22: ouvrir | K22: ouvrir
A23: Golden Wool | B23: Legendary | C23: Herd Effect | D23: DMG Reduction fluctuates between +1% and +10% every second. | E23: Weapon DMG and Status DMG total +12%, with the split changing every second. | F23: Cold/Frost Resist +20; Heat/Burn Resist -5. | G23: Gold Ore yield +20%, with a very small chance to yield a Gold Ingot. | H23: Cold/Frost Resist +20; Heat/Burn Resist -5. | I23: Roll Speed fluctuates between +10% and +25% every second. | J23: ouvrir | K23: ouvrir
A24: Grassland Wolf Skin | B24: Epic | C24: Wolf Pack | D24: Weakspot DMG Reduction +8% when in a team with more than 1 player. | E24: Weakspot DMG +4.5%. | F24: Heat/Burn Resist +10 and Max Stamina +15. | G24: Poultry Meat and Rabbit Meat yield +15%. | H24: Heat/Burn Resist +10 and Max Stamina +15. | I24: Movement Speed +8% when Stamina exceeds 80. | J24: ouvrir | K24: ouvrir
A25: Hide | B25: Uncommon | D25: Max HP +100. | E25: Melee DMG +8%. | F25: Cold Resist and Frost Resist +5. | G25: Feather yield +10%. | H25: Cold Resist and Frost Resist +5. | I25: Movement Speed +30% when blacked out. | J25: ouvrir | K25: ouvrir
A26: Highland Deer Hide | B26: Epic | C26: Stag | D26: DMG Reduction +5% while sprinting. | E26: Impact DMG +10%; doubles when Sprint Speed exceeds 120%. | F26: Cold/Frost Resist +10 and Sprint Speed +5%. | G26: Logging and Mining Speed +12%. | H26: Cold/Frost Resist +10 and Sprint Speed +5%. | I26: Sprint Speed +8%. | J26: ouvrir | K26: ouvrir
A27: Jungle Wolf Skin | B27: Epic | C27: Wolf Pack | D27: Weakspot DMG Reduction +10% while crouched. | E27: Weapon DMG +6% when Stamina is below 60. | F27: Cold/Frost Resist +10 and Max Stamina +15. | G27: Poultry Meat and Rabbit Meat yield +15%. | H27: Cold/Frost Resist +10 and Max Stamina +15. | I27: Movement Speed +30% while crouched. | J27: ouvrir | K27: ouvrir
A28: Lucky Rabbit Fur | B28: Legendary | C28: Soaring Leap | D28: Status DMG Reduction +10% while rolling. | E28: After scoring a Crit, Elemental DMG +10% for 3s. | F28: Cold/Frost Resist +10; DMG Reduction +5% when not in combat. | G28: Herb Seed yield +15%. | H28: Cold/Frost Resist +10; DMG Reduction +5% when not in combat. | I28: Jump Height +15% when Double Jump is activated. | J28: ouvrir | K28: ouvrir
A29: Lunar Deer Hide | B29: Legendary | C29: Stag | D29: While sprinting, DMG Reduction +4%; doubles if HP is below 30%. | E29: Impact DMG +13%; doubles if HP is below 30%. | F29: Cold/Frost Resist +10; when HP <30%, kills restore 5% Shield. Cooldown 8s. | G29: Lunar Whisper yield +20%; doubles if HP is below 30%. | H29: Cold/Frost Resist +10; when HP <30%, kills restore 5% Shield. Cooldown 8s. | I29: Sprint Speed +7%; doubles if HP is below 30%. | J29: ouvrir | K29: ouvrir
A30: Lunar Rabbit Fur | B30: Legendary | C30: Soaring Leap | D30: While airborne, DMG Reduction +7%; doubles if HP is below 30%. | E30: Elemental DMG +5%; doubles if HP is below 30%. | F30: Cold, Frost, Heat, and Burn Resist +5; effect doubles if HP <30%. | G30: Lunar Whisper yield +20%; doubles if HP is below 30%. | H30: Cold, Frost, Heat, and Burn Resist +5; effect doubles if HP <30%. | I30: Jump Height +8%; doubles if HP is below 30%. | J30: ouvrir | K30: ouvrir
A31: Lunar Wolf Skin | B31: Legendary | C31: Wolf Pack | D31: Weakspot DMG Reduction +6%; doubles if HP is below 30%. | E31: Weakspot DMG +4%; becomes +8% if HP is below 30%. | F31: Max Stamina +15; Hip-Fire and scoped movement speed +5%; effect doubles if HP <30%. | G31: Lunar Whisper yield +20%; doubles if HP is below 30%. | H31: Max Stamina +15; Hip-Fire and scoped movement speed +5%; effect doubles if HP <30%. | I31: Movement Speed +5%; doubles if HP is below 30%. | J31: ouvrir | K31: ouvrir
A32: Lunar Wool | B32: Legendary | C32: Herd Effect | D32: For every 10% decrease in HP, DMG Reduction +1%, up to +7%. | E32: For every 10% decrease in HP, Status DMG +1.5%, up to +10.5%. | F32: Cold/Frost Resist +15; gain Hypothermia immunity when HP <30%. | G32: Lunar Whisper yield +20%; doubles if HP is below 30%. | H32: Cold/Frost Resist +15; gain Hypothermia immunity when HP <30%. | I32: Roll Speed +8%; doubles if HP is below 30%. | J32: ouvrir | K32: ouvrir
A33: Mountain Cowhide | B33: Legendary | C33: Impacter | D33: Crit DMG Reduction +10%. | E33: Weapon DMG +8% when Stamina is at least 120. | F33: Cold/Frost Resist +15 and Max Load +20. | G33: Grain yield +15%. | H33: Cold/Frost Resist +15 and Max Load +20. | I33: Max Stamina +15. | J33: ouvrir | K33: ouvrir
A34: Mountain Wool | B34: Epic | C34: Herd Effect | D34: Non-Weakspot DMG Reduction +8% when Stamina exceeds 90. | E34: Status DMG +6% when Stamina exceeds 90. | F34: Cold/Frost Resist +15 and Dampened duration +100%. | G34: Herb yield +15%. | H34: Cold/Frost Resist +15 and Dampened duration +100%. | I34: Climb Speed and Vault Speed +10%. | J34: ouvrir | K34: ouvrir
A35: Mutant Skin | B35: Common | J35: ouvrir | K35: ouvrir | L35: legacy
A36: Polar Fox Skin | B36: Epic | C36: Fox Shadow | D36: DMG Reduction +14% when not in combat. | E36: Crit Rate +5% when not in combat. | F36: Enemies take 10% longer to notice you; DMG Reduction +5% when not in combat. | G36: Egg yield +15%. | H36: Enemies take 10% longer to notice you; DMG Reduction +5% when not in combat. | I36: Movement Speed +50% while crouched at 10°C or below. | J36: ouvrir | K36: ouvrir
A37: Rabbit Fur | B37: Uncommon | C37: Soaring Leap | D37: DMG Reduction +5% while airborne. | E37: Elemental DMG +4%. | F37: Cold Resist and Frost Resist +5. | G37: Herb Seed yield +10%. | H37: Cold Resist and Frost Resist +5. | I37: Jump Height +8%. | J37: ouvrir | K37: ouvrir
A38: Rawhide | B38: Uncommon | D38: No separate helmet perk is listed; fur rarity HP/Psi bonus still applies. | E38: No separate mask perk is listed; fur rarity HP/Psi bonus still applies. | F38: Heat Resist and Burn Resist +5. | G38: No separate gloves perk is listed; fur rarity HP/Psi bonus still applies. | H38: Heat Resist and Burn Resist +5. | I38: No separate shoes perk is listed; fur rarity HP/Psi bonus still applies. | J38: ouvrir | K38: ouvrir
A39: Reindeer Hide | B39: Uncommon | D39: DMG Reduction +3% when Load exceeds 80. | E39: Melee DMG +12% when Load exceeds 80. | F39: Cold/Frost Resist +5 and Max Load +10. | G39: Mushroom yield +10%. | H39: Cold/Frost Resist +5 and Max Load +10. | I39: Max Load +10. | J39: ouvrir | K39: ouvrir
A40: Rock Wall Wool | B40: Legendary | C40: Herd Effect | D40: Non-Weakspot DMG Reduction +7% while moving. | E40: Status DMG +6% while moving. | F40: Cold/Frost Resist +10 plus +3 per teammate. | G40: Herb yield +15%. | H40: Cold/Frost Resist +10 plus +3 per teammate. | I40: Climb Speed +15%. | J40: ouvrir | K40: ouvrir
A41: Sealskin | B41: Rare | D41: DMG Reduction +15% while swimming. | E41: Weapon DMG +8% while Dampened. | F41: Cold/Frost Resist +10 plus an additional +5 while Dampened. | G41: Stamina +25 while holding a fishing rod. | H41: Cold/Frost Resist +10 plus an additional +5 while Dampened. | I41: Swim Speed +15%. | J41: ouvrir | K41: ouvrir
A42: Shark Skin | B42: Rare | D42: DMG Reduction +5% when fighting in water. | E42: Weapon DMG +8% when fighting in water. | F42: Max Stamina +20 and Cold/Frost Resist +10. | G42: Fish Fillet yield +15%. | H42: Max Stamina +20 and Cold/Frost Resist +10. | I42: Swim Speed +20%. | J42: ouvrir | K42: ouvrir
A43: Snowfield Bear Skin | B43: Legendary | C43: Power of Bears | D43: Max HP +800 when Energy is below 60. | E43: Shock Elemental DMG +8% when Energy is below 60. | F43: Cold/Frost Resist +15; Roll Speed +10% at 10°C or below. | G43: Deer Meat, Beef, Goat Meat, and Pork yield +15%. | H43: Cold/Frost Resist +15; Roll Speed +10% at 10°C or below. | I43: Movement Speed +12% at 10°C or below. | J43: ouvrir | K43: ouvrir
A44: Squid Skin | B44: Rare | D44: While exploring water areas, enemies are less likely to target you. | E44: Status DMG +8% when fighting in water. | F44: Max Stamina +20 and Soaked Duration +1000%. | G44: Fish Fillet yield +15%. | H44: Max Stamina +20 and Soaked Duration +1000%. | I44: Max Load +30 while exploring in water. | J44: ouvrir | K44: ouvrir
A45: Starfall Cowhide | B45: Legendary | C45: Impacter | D45: Crit DMG Reduction +8%; doubles while airborne. | E45: Weapon DMG +8% when Stamina is 120 or higher; doubles while airborne. | F45: Max Load +20; Stamina recovers 5% faster while airborne. | G45: Gravity Crystal yield +10%; doubles while airborne. | H45: Max Load +20; Stamina recovers 5% faster while airborne. | I45: Max Stamina +10; Stamina consumption -5% while airborne. | J45: ouvrir | K45: ouvrir
A46: Starfall Crocodile Skin | B46: Legendary | C46: Driftwood in the Water | D46: DMG Reduction +5% at 100 Hydration; doubles while airborne. | E46: Melee DMG +10%; doubles while airborne. | F46: Heat/Burn Resist +15, plus an additional +5 while airborne. | G46: Gravity Crystal yield +10%; doubles while airborne. | H46: Heat/Burn Resist +15, plus an additional +5 while airborne. | I46: Roll Speed +10%; rolling costs 2% less Stamina. | J46: ouvrir | K46: ouvrir
A47: Starfall Down | B47: Legendary | D47: Pollution Resist +15; doubles while airborne. | E47: While airborne, Status DMG +15%. | F47: Cold/Frost Resist +15, plus an additional +5 while airborne. | G47: Gravity Crystal yield +10%; doubles while airborne. | H47: Cold/Frost Resist +15, plus an additional +5 while airborne. | I47: Glide Descent Speed -5% and Glide Horizontal Speed +5%. | J47: ouvrir | K47: ouvrir
A48: Starfall Fox Skin | B48: Legendary | C48: Fox Shadow | D48: When not in combat, DMG Reduction +10%; doubles while airborne. | E48: When not in combat, Crit Rate +10%; doubles while airborne. | F48: Enemies take 15% longer to notice you; midair kills restore 5 Stamina. | G48: Gravity Crystal yield +10%; doubles while airborne. | H48: Enemies take 15% longer to notice you; midair kills restore 5 Stamina. | I48: Crouch Movement Speed +16%; doubles outside combat. | J48: ouvrir | K48: ouvrir
A49: Starfall Fur | B49: Legendary | J49: ouvrir | K49: ouvrir | L49: legacy
A50: Thick Skin | B50: Common | J50: ouvrir | K50: ouvrir | L50: legacy
A51: Tuna Skin | B51: Epic | D51: DMG Reduction +15% while swimming. | E51: Elemental DMG +8% when fighting in water. | F51: Max Stamina +15. | G51: Fish Fillet yield +10%. | H51: Max Stamina +15. | I51: Diving Speed +30%. | J51: ouvrir
A52: Tundra Deer Hide | B52: Epic | C52: Stag | D52: DMG Reduction +3% while moving. | E52: Impact DMG +15%. | F52: Cold Resist and Frost Resist +15. | G52: Logging and Mining Speed +12%. | H52: Cold Resist and Frost Resist +15. | I52: Sprinting Stamina cost -50%. | J52: ouvrir | K52: ouvrir
A53: Valley Cowhide | B53: Legendary | C53: Impacter | D53: Upon taking Crit DMG, recover 15% HP. Cooldown 30s. | E53: Recover 30 Stamina when Stamina falls below 30. Cooldown 30s. | F53: Heat/Burn Resist +10, an additional +5 while Dampened, and Max Load +20. | G53: Grain yield +15%. | H53: Heat/Burn Resist +10, an additional +5 while Dampened, and Max Load +20. | I53: Stamina Recovery Speed +20%. | J53: ouvrir | K53: ouvrir
A54: Velvet | B54: Rare | D54: Pollution Resist +15. | E54: Status DMG +10% while Dampened. | F54: Cold/Frost Resist +15 and Dampened duration +150%. | G54: Berry yield +10%. | H54: Cold/Frost Resist +15 and Dampened duration +150%. | I54: Glide Descent Speed -10%. | J54: ouvrir | K54: ouvrir
A55: Wasteland Wolf Skin | B55: Legendary | C55: Wolf Pack | D55: Weakspot DMG Reduction +7% while moving. | E55: Weakspot DMG +6% when Stamina exceeds 90. | F55: Max Stamina +20 and Sprint Speed +5%. | G55: Poultry Meat and Rabbit Meat yield +15%. | H55: Max Stamina +20 and Sprint Speed +5%. | I55: Movement Speed +6%. | J55: ouvrir | K55: ouvrir
A56: Wolf Skin | B56: Uncommon | C56: Wolf Pack | D56: Weakspot DMG Reduction +5%. | E56: Weakspot DMG +3%. | F56: Max Stamina +15. | G56: Poultry Meat and Rabbit Meat yield +10%. | H56: Max Stamina +15. | I56: Movement Speed +4%. | J56: ouvrir | K56: ouvrir
A57: Wool | B57: Uncommon | C57: Herd Effect | D57: Non-Weakspot DMG Reduction +5%. | E57: Status DMG +4%. | F57: Cold/Frost Resist +10 and Dampened duration +100%. | G57: Herb yield +10%. | H57: Cold/Frost Resist +10 and Dampened duration +100%. | I57: Climb Speed +10%. | J57: ouvrir | K57: ouvrir

Sheet Hide sets
A1: Set | B1: In-game name | C1: Hide family | D1: Pieces | E1: Effect | F1: Hides
A2: Stag | B2: Stag | C2: Deer Hide | D2: 4 | E2: Impact Damage grants +15% Crit Damage for 5 seconds. | F2: Deer Hide, Dreamfused Deer Hide, Forest Deer Hide, Highland Deer Hide, Lunar Deer Hide, Tundra Deer Hide
A3: Wolf Pack | B3: Wolf Pack | C3: Wolf Skin | D3: 4 | E3: +6% Weakspot Damage when there is more than one party member. | F3: Dreamfused Wolf Skin, Grassland Wolf Skin, Jungle Wolf Skin, Lunar Wolf Skin, Wasteland Wolf Skin, Wolf Skin
A4: Power of Bears | B4: Power of Bears | C4: Bear Skin | D4: 4 | E4: +6% Frost & Shock Damage when the temperature is below 10°C. | F4: Bear Skin, Cave Bear Skin, Floating Ice Bear Skin, Snowfield Bear Skin
A5: Soaring Leap | B5: Soaring Leap | C5: Rabbit Fur | D5: 4 | E5: +20% Weakspot Damage while airborne. | F5: Dreamfused Rabbit Fur, Dreamy Rabbit Fur, Lucky Rabbit Fur, Lunar Rabbit Fur, Rabbit Fur
A6: Driftwood in the Water | B6: Driftwood in the Water | C6: Crocodile Skin | D6: 4 | E6: +12% Weakspot Damage while invisible. | F6: Bay Crocodile Skin, Beach Crocodile Skin, Coastal Bay Crocodile Skin, Crocodile Hide, Starfall Crocodile Skin
A7: Impacter | B7: Impacter | C7: Cowhide | D7: 4 | E7: Impact Damage consumes all Stamina and gains +1% Damage for each Stamina consumed. | F7: Cowhide, Dreamfused Cowhide, Mountain Cowhide, Starfall Cowhide, Valley Cowhide
A8: Herd Effect | B8: Herd Effect | C8: Wool | D8: 4 | E8: +2% Status Damage for each nearby ally. | F8: Dreamfused Wool, Golden Wool, Lunar Wool, Mountain Wool, Rock Wall Wool, Wool
A9: Fox Shadow | B9: Fox Shadow | C9: Fox Skin | D9: 4 | E9: +8% Physical Damage while out of combat. | F9: Desert Fox Skin, Fox Skin, Polar Fox Skin, Starfall Fox Skin
